{
  "videoId": "5RaBulFeWnI",
  "disabled": false,
  "comments": [
    {
      "id": "UgzDuGasigJqUgmiKHB4AaABAg",
      "author": "@LifeDocumentary-x7b",
      "authorImage": "https://yt3.ggpht.com/VX6MsCH8DKZ4gyPOkpzvwj2ZFQFyMv5FrVvtvsHcpuqgakZt62l20BnMnW3pEjAFJsOSJOlN=s48-c-k-c0x00ffffff-no-rj",
      "text": "The history behind this place is just as interesting as the people who live there.",
      "likeCount": 1,
      "publishedAt": "2026-06-24T03:07:35Z",
      "replyCount": 0,
      "replies": []
    }
  ]
}