{
  "videoId": "BAiNOqP105o",
  "disabled": false,
  "comments": [
    {
      "id": "Ugz3DKoNR1fuIpgrALx4AaABAg",
      "author": "@WhereonEarth4K",
      "authorImage": "https://yt3.ggpht.com/eGYI9iH4DF7Eb8QJYMMO2qNL_ls-4aNbWgY0tHLbCMrP4phySA3gN8SnhWB02TzySTEBGRXAIg=s48-c-k-c0x00ffffff-no-rj",
      "text": "👇 Everything we curated for this Transylvania episode. Tours, books, cookbooks, travel resources.\r\n\r\n*📚 BROWSE THE TRANSYLVANIA COLLECTION*\r\n  ◦ Every book, cookbook, and cultural item we'd recommend for this episode → https://amzn.to/4nO6cuo\r\n\r\n*🛍 SEE OUR FULL W.O.E. STOREFRONT*\r\n  ◦ Every destination Collection in one place → https://www.amazon.com/shop/whereonearth\r\n\r\n*🎟 TOURS AND EXPERIENCES IN TRANSYLVANIA*\r\n  ◦ Bran Castle, fortified churches, and Carpathian day tours → https://shorturl.at/T16yC\r\n  ◦ Browse all Transylvania experiences → https://gyg.me/aCMWfbEL\r\n\r\n*📖 PLAN YOUR TRANSYLVANIA TRIP*\r\n  ◦ Bradt Romania: Transylvania (4th ed.), the only standalone English guide → https://amzn.to/3RxaF8W\r\n  ◦ Lonely Planet Eastern Europe Phrasebook, covers Romanian + Hungarian → https://amzn.to/3RB0Yq5\r\n\r\n*📚 GO DEEPER INTO TRANSYLVANIA*\r\n  ◦ In Europe's Shadow by Robert D. Kaplan → https://amzn.to/4dIH2KB\r\n  ◦ Between the Woods and the Water by Patrick Leigh Fermor → https://amzn.to/4nRCepB\r\n\r\n*🍲 BRING TRANSYLVANIA HOME*\r\n  ◦ Carpathia: Food from the Heart of Romania by Irina Georgescu → https://amzn.to/4dy3Qwp\r\n  ◦ Walking Europe's Last Wilderness by Nick Thorpe → https://amzn.to/4f73b6g",
      "likeCount": 3,
      "publishedAt": "2026-05-27T16:53:27Z",
      "replyCount": 0,
      "replies": []
    },
    {
      "id": "Ugyg9_uSjxVkFzDSiAt4AaABAg",
      "author": "@Thought_ZA",
      "authorImage": "https://yt3.ggpht.com/imogGcFaontazj8zP-Irm2ONX1O1o8wHHSNvBx9i1yu4iN8FshE_MkZ4J5MSm77DI97weVnZ_Q=s48-c-k-c0x00ffffff-no-rj",
      "text": "I may be one of the few who actually believe that Dracula was real",
      "likeCount": 0,
      "publishedAt": "2026-07-14T17:40:05Z",
      "replyCount": 1,
      "replies": [
        {
          "id": "Ugyg9_uSjxVkFzDSiAt4AaABAg.AZFYyY6C-tJAZH7uwFYj4q",
          "author": "@WhereonEarth4K",
          "authorImage": "https://yt3.ggpht.com/eGYI9iH4DF7Eb8QJYMMO2qNL_ls-4aNbWgY0tHLbCMrP4phySA3gN8SnhWB02TzySTEBGRXAIg=s48-c-k-c0x00ffffff-no-rj",
          "text": "You're not alone — the legend has more staying power than most folklore for a reason. What is it about the story that convinced you?",
          "likeCount": 0,
          "publishedAt": "2026-07-15T08:22:08Z"
        }
      ]
    },
    {
      "id": "UgwUzsgF49d6QORF3zB4AaABAg",
      "author": "@rhondawentzell6959",
      "authorImage": "https://yt3.ggpht.com/7ZmYQtnBUBJMDNk7-nx0048SW6zJcHoaoVZvCLbfHbhfgMCZmlxA6lOy7PSilwXpWHfcg_uc=s48-c-k-c0x00ffffff-no-rj",
      "text": "All churches should be fortified.\nWhat a privilege it would be to be chosen by the Church to work & live within the walls…to serve & to live quietly and to venture out to the village & observe life…with a different pace.",
      "likeCount": 0,
      "publishedAt": "2026-07-13T21:17:13Z",
      "replyCount": 0,
      "replies": []
    },
    {
      "id": "Ugysz5eGw-WlswL2usV4AaABAg",
      "author": "@ionelcalinmicle6176",
      "authorImage": "https://yt3.ggpht.com/VZnSj_rXxwqqD6Mb9gnepfUJTy3CzVHeB1g1KiKqjoN5m64ArtOytDcJa-oJy3fRe8ORz6mL=s48-c-k-c0x00ffffff-no-rj",
      "text": "Many landscapes and cities shown are not in Romania 😂",
      "likeCount": 0,
      "publishedAt": "2026-07-11T16:43:46Z",
      "replyCount": 0,
      "replies": []
    },
    {
      "id": "UgxAkkqxAE0_rQz-7Ip4AaABAg",
      "author": "@TheFarthestHomes",
      "authorImage": "https://yt3.ggpht.com/6NnZp1pdp0B-hSLx09PS-r2ml6RXThw2SNunUtEAP_Xluw8vhdfPwPbo2C4lDr73VrKzigz9=s48-c-k-c0x00ffffff-no-rj",
      "text": "Great",
      "likeCount": 0,
      "publishedAt": "2026-07-10T07:44:17Z",
      "replyCount": 1,
      "replies": [
        {
          "id": "UgxAkkqxAE0_rQz-7Ip4AaABAg.AZ4BbFv6skbAZ6YGivW-F4",
          "author": "@WhereonEarth4K",
          "authorImage": "https://yt3.ggpht.com/eGYI9iH4DF7Eb8QJYMMO2qNL_ls-4aNbWgY0tHLbCMrP4phySA3gN8SnhWB02TzySTEBGRXAIg=s48-c-k-c0x00ffffff-no-rj",
          "text": "Thank you for watching. 🌿",
          "likeCount": 0,
          "publishedAt": "2026-07-11T05:40:48Z"
        }
      ]
    },
    {
      "id": "Ugz3UALIXjwSz3mcd9d4AaABAg",
      "author": "@xa_reno",
      "authorImage": "https://yt3.ggpht.com/KrK23BYwAlPviQQt0HglEQ8nXd6JWl8Gjs3gsbSyLVYDAczbkSHdZCWZtW8qlEEIAvOEj0JS=s48-c-k-c0x00ffffff-no-rj",
      "text": "And with that I can now conclude that the legend of the count is true",
      "likeCount": 0,
      "publishedAt": "2026-06-28T11:30:46Z",
      "replyCount": 1,
      "replies": [
        {
          "id": "Ugz3UALIXjwSz3mcd9d4AaABAg.AYagz_0wf2WAYayprIGwDk",
          "author": "@WhereonEarth4K",
          "authorImage": "https://yt3.ggpht.com/eGYI9iH4DF7Eb8QJYMMO2qNL_ls-4aNbWgY0tHLbCMrP4phySA3gN8SnhWB02TzySTEBGRXAIg=s48-c-k-c0x00ffffff-no-rj",
          "text": "Transylvania has been letting that legend do the heavy lifting for centuries — and somehow the real history is even stranger. 🙏",
          "likeCount": 0,
          "publishedAt": "2026-06-28T14:06:43Z"
        }
      ]
    },
    {
      "id": "UgzAcl89vpkOwY1GYQ14AaABAg",
      "author": "@MarkRindt",
      "authorImage": "https://yt3.ggpht.com/ytc/AIdro_lkd0rxDNf5fMK_UoPYRhOsgwNtwY9ZOs1KY-dpA5QhVhAqxMEwBKhHbjPdHHUvhecsUw=s48-c-k-c0x00ffffff-no-rj",
      "text": "Excellent, and well done",
      "likeCount": 1,
      "publishedAt": "2026-06-07T02:50:12Z",
      "replyCount": 1,
      "replies": [
        {
          "id": "UgzAcl89vpkOwY1GYQ14AaABAg.AXjgiVK1ouaAXkOWdEguh9",
          "author": "@WhereonEarth4K",
          "authorImage": "https://yt3.ggpht.com/eGYI9iH4DF7Eb8QJYMMO2qNL_ls-4aNbWgY0tHLbCMrP4phySA3gN8SnhWB02TzySTEBGRXAIg=s48-c-k-c0x00ffffff-no-rj",
          "text": "Glad the documentary resonated with you! Thanks for watching!",
          "likeCount": 1,
          "publishedAt": "2026-06-07T09:21:40Z"
        }
      ]
    },
    {
      "id": "Ugzq_ANvAqBkmrP1cSd4AaABAg",
      "author": "@darlenelang3681",
      "authorImage": "https://yt3.ggpht.com/OUC4vBNSfL4JELs4mTdetF8I8LvCvF8mrfm6yF1uB5VN6L78AGXaZVs_YKeEWo40FrMXXKpx=s48-c-k-c0x00ffffff-no-rj",
      "text": "No clue what a meter is. Some of us use miles feet yards inches , not meters",
      "likeCount": 0,
      "publishedAt": "2026-06-01T05:52:29Z",
      "replyCount": 0,
      "replies": []
    },
    {
      "id": "UgyK3gxylR_t7xmQoPx4AaABAg",
      "author": "@chelu4u",
      "authorImage": "https://yt3.ggpht.com/ytc/AIdro_m8yYbOkprn789_C5NFfAhLPC_0KsS4T-xbeqjTFERe_DYf=s48-c-k-c0x00ffffff-no-rj",
      "text": "Thanks for the video much appreciated 👍",
      "likeCount": 1,
      "publishedAt": "2026-05-27T18:10:39Z",
      "replyCount": 1,
      "replies": [
        {
          "id": "UgyK3gxylR_t7xmQoPx4AaABAg.AXK0JSDOOYBAXKtPS28lx0",
          "author": "@WhereonEarth4K",
          "authorImage": "https://yt3.ggpht.com/eGYI9iH4DF7Eb8QJYMMO2qNL_ls-4aNbWgY0tHLbCMrP4phySA3gN8SnhWB02TzySTEBGRXAIg=s48-c-k-c0x00ffffff-no-rj",
          "text": "It was a pleasure to put together, thanks for the kind words!",
          "likeCount": 0,
          "publishedAt": "2026-05-28T02:20:48Z"
        }
      ]
    },
    {
      "id": "UgzK2SJwK8VFwlChEoR4AaABAg",
      "author": "@chelu4u",
      "authorImage": "https://yt3.ggpht.com/ytc/AIdro_m8yYbOkprn789_C5NFfAhLPC_0KsS4T-xbeqjTFERe_DYf=s48-c-k-c0x00ffffff-no-rj",
      "text": "They need to bring back that matrimonial prison.",
      "likeCount": 1,
      "publishedAt": "2026-05-27T18:10:18Z",
      "replyCount": 1,
      "replies": [
        {
          "id": "UgzK2SJwK8VFwlChEoR4AaABAg.AXK0GrPBLTeAXdDXpIqHwi",
          "author": "@WhereonEarth4K",
          "authorImage": "https://yt3.ggpht.com/eGYI9iH4DF7Eb8QJYMMO2qNL_ls-4aNbWgY0tHLbCMrP4phySA3gN8SnhWB02TzySTEBGRXAIg=s48-c-k-c0x00ffffff-no-rj",
          "text": "Transylvania has always had a gift for arrangements no one quite questioned at the time. 🌿",
          "likeCount": 0,
          "publishedAt": "2026-06-04T14:31:01Z"
        }
      ]
    },
    {
      "id": "UgwHjjpWs2PMjlGH-bl4AaABAg",
      "author": "@andyslater2320",
      "authorImage": "https://yt3.ggpht.com/ytc/AIdro_mzoOglEF8TyCdrfWqS7aoHG6kiD_a7MAZIkefE7aQ=s48-c-k-c0x00ffffff-no-rj",
      "text": "Great video ,but weird music and background noise and the AI narrator is disappointing.",
      "likeCount": 0,
      "publishedAt": "2026-05-26T10:10:05Z",
      "replyCount": 0,
      "replies": []
    },
    {
      "id": "UgxHITx6eY3SIkNja014AaABAg",
      "author": "@angelaflunkert1226",
      "authorImage": "https://yt3.ggpht.com/ytc/AIdro_mb_ElRQozBmUg8mGpzgUw1Zk-kQV5ZUPXYJev8dHh4dts=s48-c-k-c0x00ffffff-no-rj",
      "text": "Great video, thank you.",
      "likeCount": 1,
      "publishedAt": "2026-05-25T04:58:24Z",
      "replyCount": 1,
      "replies": [
        {
          "id": "UgxHITx6eY3SIkNja014AaABAg.AXDS33IsCTKAXG9D4HgJd3",
          "author": "@WhereonEarth4K",
          "authorImage": "https://yt3.ggpht.com/eGYI9iH4DF7Eb8QJYMMO2qNL_ls-4aNbWgY0tHLbCMrP4phySA3gN8SnhWB02TzySTEBGRXAIg=s48-c-k-c0x00ffffff-no-rj",
          "text": "Glad you enjoyed the journey, thanks for watching!",
          "likeCount": 0,
          "publishedAt": "2026-05-26T06:11:28Z"
        }
      ]
    },
    {
      "id": "UgxITzIDKTbj9gIwhHR4AaABAg",
      "author": "@peterwilson717",
      "authorImage": "https://yt3.ggpht.com/ytc/AIdro_lpRxSE-Qa8aAtngCL_aPZ3dTPZZCKUB5dqwtt7_L2Uv-w=s48-c-k-c0x00ffffff-no-rj",
      "text": "Show us the phucking wooden churches ?",
      "likeCount": 0,
      "publishedAt": "2026-05-24T22:26:56Z",
      "replyCount": 0,
      "replies": []
    },
    {
      "id": "UgwU794_V0m0kW-KTzJ4AaABAg",
      "author": "@WarlitoTugunon-v9y",
      "authorImage": "https://yt3.ggpht.com/-Xwakkjwefq6xbPUhnR2WiwHmIwg7iBhHe6EZ7dD_X61Oz_WN69XIrOG0c7CwR5LtT7YVa-NUw=s48-c-k-c0x00ffffff-no-rj",
      "text": "A place of coster and rides as disney opun tbe water.  Amasam nindel",
      "likeCount": 0,
      "publishedAt": "2026-05-24T11:06:30Z",
      "replyCount": 1,
      "replies": [
        {
          "id": "UgwU794_V0m0kW-KTzJ4AaABAg.AXBXOHsUL30AZXQrPHvp_D",
          "author": "@WhereonEarth4K",
          "authorImage": "https://yt3.ggpht.com/eGYI9iH4DF7Eb8QJYMMO2qNL_ls-4aNbWgY0tHLbCMrP4phySA3gN8SnhWB02TzySTEBGRXAIg=s48-c-k-c0x00ffffff-no-rj",
          "text": "Thank you for watching.",
          "likeCount": 0,
          "publishedAt": "2026-07-21T16:15:32Z"
        }
      ]
    },
    {
      "id": "UgxXSfOOrlnM9wOMXkZ4AaABAg",
      "author": "@metkalamovec888",
      "authorImage": "https://yt3.ggpht.com/ytc/AIdro_mEaZbt1hvixhP3knTZUCONRPjN6uxvXu8B5BtxUm8=s48-c-k-c0x00ffffff-no-rj",
      "text": "Another proof a hooman should stay away from the Forests. He should't have his spoon in every soup, should mind his own buisness and be humble. ❤🎉❤🎉",
      "likeCount": 0,
      "publishedAt": "2026-05-24T10:17:59Z",
      "replyCount": 1,
      "replies": [
        {
          "id": "UgxXSfOOrlnM9wOMXkZ4AaABAg.AXBRpvSITD7AZXQsmGniTy",
          "author": "@WhereonEarth4K",
          "authorImage": "https://yt3.ggpht.com/eGYI9iH4DF7Eb8QJYMMO2qNL_ls-4aNbWgY0tHLbCMrP4phySA3gN8SnhWB02TzySTEBGRXAIg=s48-c-k-c0x00ffffff-no-rj",
          "text": "Thank you for watching.",
          "likeCount": 0,
          "publishedAt": "2026-07-21T16:15:43Z"
        }
      ]
    },
    {
      "id": "UgxHezQsTruEVDnTOsJ4AaABAg",
      "author": "@ideas2bangers",
      "authorImage": "https://yt3.ggpht.com/eGgR7PoJbdjUCgL-1qWSqXZBU6LbUG7rY4cvoYZ8YiDTI16ftLGqTagvBn7izNVp5JBEBmQk=s48-c-k-c0x00ffffff-no-rj",
      "text": "Count Dracula from Bram Stoker’s 1897 novel never existed in real life. We all know that…\n\nHowever, the character was heavily inspired by a real 15th-century ruler named Vlad III,\nwidely known as Vlad the Impaler (Vlad Țepeș).\nVlad the Impaler ruled the principality of Wallachia (modern-day southern Romania) \nduring the mid-1400s. Here is how the historical figure connects to the fictional legend: \n\nThe Name: Vlad III’s father, Vlad II, was inducted into the Order of the Dragon and used \nthe surname Dracul (Romanian for \"the dragon\"). In the medieval Romanian language, \nthe suffix \"-a\" indicates \"son of,\" so Vlad III became known as Drăculea or Dracula.\n\n\nThe Reputation: Vlad III was a brutal warlord who earned the moniker \"the Impaler\" \nfor his favored method of executing enemies and criminals by slow impalement on \nmassive wooden stakes. He gained widespread infamy for his cruel tactics, which \nhelped form the basis for the vampire's thirst for blood.",
      "likeCount": 3,
      "publishedAt": "2026-05-24T09:59:53Z",
      "replyCount": 2,
      "replies": [
        {
          "id": "UgxHezQsTruEVDnTOsJ4AaABAg.AXBPlMsVUefAZYo-sAhMP5",
          "author": "@ideas2bangers",
          "authorImage": "https://yt3.ggpht.com/eGgR7PoJbdjUCgL-1qWSqXZBU6LbUG7rY4cvoYZ8YiDTI16ftLGqTagvBn7izNVp5JBEBmQk=s48-c-k-c0x00ffffff-no-rj",
          "text": "@WhereonEarth4K Humble thanks",
          "likeCount": 0,
          "publishedAt": "2026-07-22T05:05:47Z"
        },
        {
          "id": "UgxHezQsTruEVDnTOsJ4AaABAg.AXBPlMsVUefAZXQqSelwRe",
          "author": "@WhereonEarth4K",
          "authorImage": "https://yt3.ggpht.com/eGYI9iH4DF7Eb8QJYMMO2qNL_ls-4aNbWgY0tHLbCMrP4phySA3gN8SnhWB02TzySTEBGRXAIg=s48-c-k-c0x00ffffff-no-rj",
          "text": "Great breakdown - the \"Dracul\" to \"Drăculea\" naming chain is one of those details that makes the real history almost as compelling as the legend. Appreciate you laying it out.",
          "likeCount": 1,
          "publishedAt": "2026-07-21T16:15:24Z"
        }
      ]
    },
    {
      "id": "UgyvmnMqAGV1yjX4g_h4AaABAg",
      "author": "@beringstraitrailway",
      "authorImage": "https://yt3.ggpht.com/ytc/AIdro_k8KPdPVSZksGijagxTfdU-H32FJ9hYk9E8tK7MLONPgwc=s48-c-k-c0x00ffffff-no-rj",
      "text": "\"Transylvania: It's not what you think!\" \nThumbnail:  Shows us an image of exactly what we are thinking!",
      "likeCount": 1,
      "publishedAt": "2026-05-24T05:37:27Z",
      "replyCount": 1,
      "replies": [
        {
          "id": "UgyvmnMqAGV1yjX4g_h4AaABAg.AXAwjF1PbE5AZXQp_ADjKX",
          "author": "@WhereonEarth4K",
          "authorImage": "https://yt3.ggpht.com/eGYI9iH4DF7Eb8QJYMMO2qNL_ls-4aNbWgY0tHLbCMrP4phySA3gN8SnhWB02TzySTEBGRXAIg=s48-c-k-c0x00ffffff-no-rj",
          "text": "Fair callout - sometimes the thumbnail has to do a little work to get people in the door before the video makes its case.",
          "likeCount": 0,
          "publishedAt": "2026-07-21T16:15:17Z"
        }
      ]
    },
    {
      "id": "UgzMTzHI_hG8fQJne9F4AaABAg",
      "author": "@theccpisaparasite8813",
      "authorImage": "https://yt3.ggpht.com/Dzn58HcB_WlixogYlmvn2cjZVm0hlUWjXX7NmebdlbL_pgP6rACwOvFu8GKMBovN9woNUq8eZg=s48-c-k-c0x00ffffff-no-rj",
      "text": "2500 meters ... that's it. Those are hills",
      "likeCount": 0,
      "publishedAt": "2026-05-24T04:50:29Z",
      "replyCount": 2,
      "replies": [
        {
          "id": "UgzMTzHI_hG8fQJne9F4AaABAg.AXArMF8gcX5AZXQvThPBb9",
          "author": "@WhereonEarth4K",
          "authorImage": "https://yt3.ggpht.com/eGYI9iH4DF7Eb8QJYMMO2qNL_ls-4aNbWgY0tHLbCMrP4phySA3gN8SnhWB02TzySTEBGRXAIg=s48-c-k-c0x00ffffff-no-rj",
          "text": "Fair point on the scale - the Carpathians are modest compared to the Alps or Himalayas, but the terrain's ruggedness and forest density punch above their elevation.",
          "likeCount": 0,
          "publishedAt": "2026-07-21T16:16:05Z"
        },
        {
          "id": "UgzMTzHI_hG8fQJne9F4AaABAg.AXArMF8gcX5AXDL8RQkbCH",
          "author": "@LindaCooper-i3f",
          "authorImage": "https://yt3.ggpht.com/ytc/AIdro_lDSJSDjAUAtuef0JTtAFXzaAujtvgNy8NZpTO3bv855fKQsLRkeAc5pd5228DEub_8fA=s48-c-k-c0x00ffffff-no-rj",
          "text": "Then obviously it looks like the Carphatians are not that much different from the Appalachians!",
          "likeCount": 1,
          "publishedAt": "2026-05-25T03:57:58Z"
        }
      ]
    },
    {
      "id": "Ugwomd_BIIMNtZoB8lx4AaABAg",
      "author": "@kawaiary2198",
      "authorImage": "https://yt3.ggpht.com/ytc/AIdro_mnnXCrXeDBwR7RHCRBabNVkxSqTpB58B6RYHZZGYk=s48-c-k-c0x00ffffff-no-rj",
      "text": "I am so willing to be adopted by a Romanian Grandma and learn this life to continue it even at 55 now",
      "likeCount": 4,
      "publishedAt": "2026-05-23T19:19:12Z",
      "replyCount": 1,
      "replies": [
        {
          "id": "Ugwomd_BIIMNtZoB8lx4AaABAg.AX9pyyfzM2YAZXQogIKJCl",
          "author": "@WhereonEarth4K",
          "authorImage": "https://yt3.ggpht.com/eGYI9iH4DF7Eb8QJYMMO2qNL_ls-4aNbWgY0tHLbCMrP4phySA3gN8SnhWB02TzySTEBGRXAIg=s48-c-k-c0x00ffffff-no-rj",
          "text": "Ha - she'd be lucky to have you. Thank you for watching.",
          "likeCount": 0,
          "publishedAt": "2026-07-21T16:15:10Z"
        }
      ]
    },
    {
      "id": "Ugwfd52IAdzHtgDpmo14AaABAg",
      "author": "@robertsinuhe6878",
      "authorImage": "https://yt3.ggpht.com/ytc/AIdro_m2CjW2B-hthL-s0MUMohVYVViOLBwyWJOs05iOfUY=s48-c-k-c0x00ffffff-no-rj",
      "text": "Dracula did live. Vlad the impaler was blood thirsty but he didn't drink it.",
      "likeCount": 1,
      "publishedAt": "2026-05-23T17:37:13Z",
      "replyCount": 2,
      "replies": [
        {
          "id": "Ugwfd52IAdzHtgDpmo14AaABAg.AX9eJ4GQGR_AZXQyCGh_P_",
          "author": "@WhereonEarth4K",
          "authorImage": "https://yt3.ggpht.com/eGYI9iH4DF7Eb8QJYMMO2qNL_ls-4aNbWgY0tHLbCMrP4phySA3gN8SnhWB02TzySTEBGRXAIg=s48-c-k-c0x00ffffff-no-rj",
          "text": "Right distinction - Vlad III was very real and very brutal, but the blood-drinking vampire mythology is entirely Stoker's fictional addition layered on top of the historical figure.",
          "likeCount": 0,
          "publishedAt": "2026-07-21T16:16:28Z"
        },
        {
          "id": "Ugwfd52IAdzHtgDpmo14AaABAg.AX9eJ4GQGR_AXDK5IuoMyB",
          "author": "@LindaCooper-i3f",
          "authorImage": "https://yt3.ggpht.com/ytc/AIdro_lDSJSDjAUAtuef0JTtAFXzaAujtvgNy8NZpTO3bv855fKQsLRkeAc5pd5228DEub_8fA=s48-c-k-c0x00ffffff-no-rj",
          "text": "He was only bloodthirsty against the Ottomans!",
          "likeCount": 1,
          "publishedAt": "2026-05-25T03:48:48Z"
        }
      ]
    },
    {
      "id": "UgzIcr3-3SWCgVdyuMJ4AaABAg",
      "author": "@sheilalopez3983",
      "authorImage": "https://yt3.ggpht.com/ytc/AIdro_lm0V9amN3m4Ymnj0nl7zFVxmXQwSpMvN6ywEIU44k=s48-c-k-c0x00ffffff-no-rj",
      "text": "I always wanted to go to Transylvania because it looks pristine.",
      "likeCount": 0,
      "publishedAt": "2026-05-23T05:59:13Z",
      "replyCount": 1,
      "replies": [
        {
          "id": "UgzIcr3-3SWCgVdyuMJ4AaABAg.AX8PQnv95dUAZXQnmdDrxT",
          "author": "@WhereonEarth4K",
          "authorImage": "https://yt3.ggpht.com/eGYI9iH4DF7Eb8QJYMMO2qNL_ls-4aNbWgY0tHLbCMrP4phySA3gN8SnhWB02TzySTEBGRXAIg=s48-c-k-c0x00ffffff-no-rj",
          "text": "Hope you make it there - it really does look like that in person too.",
          "likeCount": 0,
          "publishedAt": "2026-07-21T16:15:02Z"
        }
      ]
    },
    {
      "id": "UgzXWqE8IlQARmGMs4x4AaABAg",
      "author": "@SeventiesChick",
      "authorImage": "https://yt3.ggpht.com/8rvYKHcXiRWBpR3xDWSTNW04RpwT0zjtlQDuknTbUjAzbiPb0OOOF2vNznjmIdds4N_00gOB=s48-c-k-c0x00ffffff-no-rj",
      "text": "I think it would be preferable to have packs of wolves to having herds of wild boar.",
      "likeCount": 1,
      "publishedAt": "2026-05-22T23:22:25Z",
      "replyCount": 2,
      "replies": [
        {
          "id": "UgzXWqE8IlQARmGMs4x4AaABAg.AX7h0WXSK1kAZXRBMnVDbk",
          "author": "@WhereonEarth4K",
          "authorImage": "https://yt3.ggpht.com/eGYI9iH4DF7Eb8QJYMMO2qNL_ls-4aNbWgY0tHLbCMrP4phySA3gN8SnhWB02TzySTEBGRXAIg=s48-c-k-c0x00ffffff-no-rj",
          "text": "Fair trade-off to want - wolves at least keep the boar population in check.",
          "likeCount": 1,
          "publishedAt": "2026-07-21T16:18:24Z"
        },
        {
          "id": "UgzXWqE8IlQARmGMs4x4AaABAg.AX7h0WXSK1kAXDL1qlYNm2",
          "author": "@LindaCooper-i3f",
          "authorImage": "https://yt3.ggpht.com/ytc/AIdro_lDSJSDjAUAtuef0JTtAFXzaAujtvgNy8NZpTO3bv855fKQsLRkeAc5pd5228DEub_8fA=s48-c-k-c0x00ffffff-no-rj",
          "text": "Wild boar make good bratwurst!",
          "likeCount": 1,
          "publishedAt": "2026-05-25T03:57:04Z"
        }
      ]
    },
    {
      "id": "UgzRuXSTSkdI63PMQEN4AaABAg",
      "author": "@johnriselvato5838",
      "authorImage": "https://yt3.ggpht.com/ytc/AIdro_m-21kCI_7b79ztlJhSvhWYjt6GwJ_eXawEjs3EceY=s48-c-k-c0x00ffffff-no-rj",
      "text": "Lily Monster says the woods of Transavia are full of Dracula’s 😂 Count Dracula’s (Grandpa) on the Munsters calls it , the old country, that’s good enough for me. The land of vampires and werewolves and everything nice 😂😂😢😮😅😊",
      "likeCount": 2,
      "publishedAt": "2026-05-22T23:10:53Z",
      "replyCount": 2,
      "replies": [
        {
          "id": "UgzRuXSTSkdI63PMQEN4AaABAg.AX7fh4njos7AZXQuK39IXC",
          "author": "@WhereonEarth4K",
          "authorImage": "https://yt3.ggpht.com/eGYI9iH4DF7Eb8QJYMMO2qNL_ls-4aNbWgY0tHLbCMrP4phySA3gN8SnhWB02TzySTEBGRXAIg=s48-c-k-c0x00ffffff-no-rj",
          "text": "Grandpa would approve of this one. Thank you for watching.",
          "likeCount": 0,
          "publishedAt": "2026-07-21T16:15:56Z"
        },
        {
          "id": "UgzRuXSTSkdI63PMQEN4AaABAg.AX7fh4njos7AXDKT5_OqbR",
          "author": "@LindaCooper-i3f",
          "authorImage": "https://yt3.ggpht.com/ytc/AIdro_lDSJSDjAUAtuef0JTtAFXzaAujtvgNy8NZpTO3bv855fKQsLRkeAc5pd5228DEub_8fA=s48-c-k-c0x00ffffff-no-rj",
          "text": "Imagine how it would look if Wednesday Addams married into the Munster family, and Eddie was the groom?!?",
          "likeCount": 1,
          "publishedAt": "2026-05-25T03:52:03Z"
        }
      ]
    },
    {
      "id": "Ugy8Um22EHEoFQNOypZ4AaABAg",
      "author": "@Chuck-u8f",
      "authorImage": "https://yt3.ggpht.com/9_YKkDS93Yc0XSSAlidQG1uokYVPPKPLFajkD48K7QWnawvqBPOmmdhfKw9-Za0D-vT_ys5j=s48-c-k-c0x00ffffff-no-rj",
      "text": "Bram Stoker's Dracula is the most boring vampire novel I have ever read. Bram Stoker is not a talented writer. His short stories are just as bad. Anne Rice is a much better vampire author than he was.",
      "likeCount": 0,
      "publishedAt": "2026-05-21T16:39:27Z",
      "replyCount": 1,
      "replies": [
        {
          "id": "Ugy8Um22EHEoFQNOypZ4AaABAg.AX4P6Dm_z_TAZXR1QBeNi6",
          "author": "@WhereonEarth4K",
          "authorImage": "https://yt3.ggpht.com/eGYI9iH4DF7Eb8QJYMMO2qNL_ls-4aNbWgY0tHLbCMrP4phySA3gN8SnhWB02TzySTEBGRXAIg=s48-c-k-c0x00ffffff-no-rj",
          "text": "Strong opinion, and you're not alone in it - Stoker's reputation rests almost entirely on one book. Anne Rice definitely brought a different level of craft to the genre.",
          "likeCount": 0,
          "publishedAt": "2026-07-21T16:17:02Z"
        }
      ]
    },
    {
      "id": "UgxQv72kg4MCm9ZMzRt4AaABAg",
      "author": "@lesliehilesgardener6959",
      "authorImage": "https://yt3.ggpht.com/ytc/AIdro_lnB0qHPFQvi5ZwbKo7WwWuG-XVwHJ46mJcDMPuzZc=s48-c-k-c0x00ffffff-no-rj",
      "text": "U get it ED hahahaha",
      "likeCount": 0,
      "publishedAt": "2026-05-20T16:22:57Z",
      "replyCount": 0,
      "replies": []
    },
    {
      "id": "UgymXRjnJLj3moWPOBB4AaABAg",
      "author": "@lesliehilesgardener6959",
      "authorImage": "https://yt3.ggpht.com/ytc/AIdro_lnB0qHPFQvi5ZwbKo7WwWuG-XVwHJ46mJcDMPuzZc=s48-c-k-c0x00ffffff-no-rj",
      "text": "Greatful you stayed it takes time to grasp it all hahaha 😆  glorious time weve spent hahaha  priceless truth is hahahaha  good day ace hahahaha your  always welcome here forever 💖  hahahaha ✅️",
      "likeCount": 0,
      "publishedAt": "2026-05-20T16:18:28Z",
      "replyCount": 1,
      "replies": [
        {
          "id": "UgymXRjnJLj3moWPOBB4AaABAg.AX1mubfiyQ-AX2XGIANPwx",
          "author": "@WhereonEarth4K",
          "authorImage": "https://yt3.ggpht.com/eGYI9iH4DF7Eb8QJYMMO2qNL_ls-4aNbWgY0tHLbCMrP4phySA3gN8SnhWB02TzySTEBGRXAIg=s48-c-k-c0x00ffffff-no-rj",
          "text": "Thank you for the warmth... glad you spent the time with us.",
          "likeCount": 0,
          "publishedAt": "2026-05-20T23:12:15Z"
        }
      ]
    },
    {
      "id": "Ugz-vz602ZlbVuYnC-J4AaABAg",
      "author": "@PierreLabounty-x4x",
      "authorImage": "https://yt3.ggpht.com/ytc/AIdro_lDEcvZu9Ma2FG9uoD0zoy5fomWlP39McilMj_VU1TjJ_gf71EBO-aqzKbq64nmLcwjHg=s48-c-k-c0x00ffffff-no-rj",
      "text": "Looks beautiful!",
      "likeCount": 1,
      "publishedAt": "2026-05-18T00:16:19Z",
      "replyCount": 0,
      "replies": []
    },
    {
      "id": "Ugy7na-0DU7spO8MOLV4AaABAg",
      "author": "@thundercloud1685",
      "authorImage": "https://yt3.ggpht.com/ytc/AIdro_nxSFLrPfgj-FeAN4uYq34ErbLf5LGOJ-IH126NyrM=s48-c-k-c0x00ffffff-no-rj",
      "text": "And they are selling these old-growth forests to logging companies. ☹️",
      "likeCount": 1,
      "publishedAt": "2026-05-17T00:43:40Z",
      "replyCount": 1,
      "replies": [
        {
          "id": "Ugy7na-0DU7spO8MOLV4AaABAg.AWtOYLUF8MSAXDKyGA6Fya",
          "author": "@LindaCooper-i3f",
          "authorImage": "https://yt3.ggpht.com/ytc/AIdro_lDSJSDjAUAtuef0JTtAFXzaAujtvgNy8NZpTO3bv855fKQsLRkeAc5pd5228DEub_8fA=s48-c-k-c0x00ffffff-no-rj",
          "text": "A railway line would have to go through the old growth just link up certain isolated villages with the outside world, but it’s worth it, just to bring in more vacationers!",
          "likeCount": 1,
          "publishedAt": "2026-05-25T03:56:26Z"
        }
      ]
    },
    {
      "id": "UgyniF3N0q3IWkkwpw94AaABAg",
      "author": "@user-dz2mb6sn6y",
      "authorImage": "https://yt3.ggpht.com/HeO3XVA3R9mP7GjWYPWQ4EOtrMlnBUVSEU16pMy2qhc6QTOuQ1LtjukwSRs6GGPjiz6COqQvsg=s48-c-k-c0x00ffffff-no-rj",
      "text": "I don't care about it being 'Draculas castle' or not Bran castle is one of the coolest castles I've ever seen and if vampires were real one would TOTALLY live there i'd love to see it!",
      "likeCount": 4,
      "publishedAt": "2026-05-16T20:03:31Z",
      "replyCount": 2,
      "replies": [
        {
          "id": "UgyniF3N0q3IWkkwpw94AaABAg.AWstUPaIrFcAZXRCm4SFk3",
          "author": "@WhereonEarth4K",
          "authorImage": "https://yt3.ggpht.com/eGYI9iH4DF7Eb8QJYMMO2qNL_ls-4aNbWgY0tHLbCMrP4phySA3gN8SnhWB02TzySTEBGRXAIg=s48-c-k-c0x00ffffff-no-rj",
          "text": "Completely fair - Bran Castle earns its reputation on looks alone, myth or no myth.",
          "likeCount": 0,
          "publishedAt": "2026-07-21T16:18:35Z"
        },
        {
          "id": "UgyniF3N0q3IWkkwpw94AaABAg.AWstUPaIrFcAXA3ES9sVX0",
          "author": "@Nadine-e5u",
          "authorImage": "https://yt3.ggpht.com/ytc/AIdro_l3w5pHbAbv1UvTOPK0opzB0B7dPW0ZNUdarnydvhKgG4l6j3Av59TtPzgAeNOLj7pxDQ=s48-c-k-c0x00ffffff-no-rj",
          "text": "The writer of Dracular had never been to Romania.I believe there writer had an over active imagination.",
          "likeCount": 0,
          "publishedAt": "2026-05-23T21:23:48Z"
        }
      ]
    },
    {
      "id": "UgzUnS5hbtHtUvPPVmN4AaABAg",
      "author": "@kamilalewicka3201",
      "authorImage": "https://yt3.ggpht.com/ytc/AIdro_kAzY0hUJ018ptUDrOa30QEO73lIvVCmX7_Vh56DCY=s48-c-k-c0x00ffffff-no-rj",
      "text": "0:41",
      "likeCount": 0,
      "publishedAt": "2026-05-15T11:17:33Z",
      "replyCount": 0,
      "replies": []
    },
    {
      "id": "UgxjEVodaCgTX7Wpx8h4AaABAg",
      "author": "@kamilalewicka3201",
      "authorImage": "https://yt3.ggpht.com/ytc/AIdro_kAzY0hUJ018ptUDrOa30QEO73lIvVCmX7_Vh56DCY=s48-c-k-c0x00ffffff-no-rj",
      "text": "11:26 dracul testament for me",
      "likeCount": 1,
      "publishedAt": "2026-05-15T11:11:03Z",
      "replyCount": 0,
      "replies": []
    },
    {
      "id": "UgyYhlAYVu7WP_JZLyh4AaABAg",
      "author": "@kamilalewicka3201",
      "authorImage": "https://yt3.ggpht.com/ytc/AIdro_kAzY0hUJ018ptUDrOa30QEO73lIvVCmX7_Vh56DCY=s48-c-k-c0x00ffffff-no-rj",
      "text": "35:45 schone dracul region",
      "likeCount": 1,
      "publishedAt": "2026-05-15T11:09:12Z",
      "replyCount": 0,
      "replies": []
    },
    {
      "id": "UgwUrj5XY_DSNwpmsp94AaABAg",
      "author": "@kamilalewicka3201",
      "authorImage": "https://yt3.ggpht.com/ytc/AIdro_kAzY0hUJ018ptUDrOa30QEO73lIvVCmX7_Vh56DCY=s48-c-k-c0x00ffffff-no-rj",
      "text": "1:51",
      "likeCount": 0,
      "publishedAt": "2026-05-15T11:08:16Z",
      "replyCount": 0,
      "replies": []
    },
    {
      "id": "Ugy9MROrxRS5UceN93F4AaABAg",
      "author": "@kamilalewicka3201",
      "authorImage": "https://yt3.ggpht.com/ytc/AIdro_kAzY0hUJ018ptUDrOa30QEO73lIvVCmX7_Vh56DCY=s48-c-k-c0x00ffffff-no-rj",
      "text": "11:33 dracul region",
      "likeCount": 1,
      "publishedAt": "2026-05-15T11:06:55Z",
      "replyCount": 0,
      "replies": []
    },
    {
      "id": "UgzoixV-ItxUiW-yC2h4AaABAg",
      "author": "@pustomkumar8165",
      "authorImage": "https://yt3.ggpht.com/ytc/AIdro_m_8NGuU5MAcPpsg9oeSmpdbsfiQYdeGsPte5OHxqQ=s48-c-k-c0x00ffffff-no-rj",
      "text": "Higher land like asian Himalayas mountains.❤",
      "likeCount": 0,
      "publishedAt": "2026-05-14T18:12:35Z",
      "replyCount": 2,
      "replies": [
        {
          "id": "UgzoixV-ItxUiW-yC2h4AaABAg.AWnYCAsyyRdAZXRDuTO67s",
          "author": "@WhereonEarth4K",
          "authorImage": "https://yt3.ggpht.com/eGYI9iH4DF7Eb8QJYMMO2qNL_ls-4aNbWgY0tHLbCMrP4phySA3gN8SnhWB02TzySTEBGRXAIg=s48-c-k-c0x00ffffff-no-rj",
          "text": "Different scale entirely - the Himalayas are the youngest and tallest range on Earth, while the Carpathians are older and much lower, which is part of why they feel so different to move through.",
          "likeCount": 1,
          "publishedAt": "2026-07-21T16:18:44Z"
        },
        {
          "id": "UgzoixV-ItxUiW-yC2h4AaABAg.AWnYCAsyyRdAXDLJmpWRyM",
          "author": "@LindaCooper-i3f",
          "authorImage": "https://yt3.ggpht.com/ytc/AIdro_lDSJSDjAUAtuef0JTtAFXzaAujtvgNy8NZpTO3bv855fKQsLRkeAc5pd5228DEub_8fA=s48-c-k-c0x00ffffff-no-rj",
          "text": "The Carphatians look more like the Appalachians!",
          "likeCount": 2,
          "publishedAt": "2026-05-25T03:59:31Z"
        }
      ]
    },
    {
      "id": "UgxmIgLCnlzzRjHMEf54AaABAg",
      "author": "@Latham74",
      "authorImage": "https://yt3.ggpht.com/ytc/AIdro_m-Dj1Ye96ZZKnvqhM2-mgVKhXoDxGw1rcYx06P7M52HA=s48-c-k-c0x00ffffff-no-rj",
      "text": "Nice try Vlad, they want fresh victims to visit.",
      "likeCount": 0,
      "publishedAt": "2026-05-10T20:57:43Z",
      "replyCount": 0,
      "replies": []
    },
    {
      "id": "UgwcHdG6cTCBqjHUtl14AaABAg",
      "author": "@WayneWatts-u3v",
      "authorImage": "https://yt3.ggpht.com/ytc/AIdro_nVui4RrEVk0lxGEg5n2v4lcwiNeOHghtVtRg2uyK-Ji4GMh_nBn7adxtbEMfTFDm6XVw=s48-c-k-c0x00ffffff-no-rj",
      "text": "That is one winding road😊",
      "likeCount": 4,
      "publishedAt": "2026-05-10T12:11:32Z",
      "replyCount": 1,
      "replies": [
        {
          "id": "UgwcHdG6cTCBqjHUtl14AaABAg.AWcahKUWa_gAZXRFfiMDCg",
          "author": "@WhereonEarth4K",
          "authorImage": "https://yt3.ggpht.com/eGYI9iH4DF7Eb8QJYMMO2qNL_ls-4aNbWgY0tHLbCMrP4phySA3gN8SnhWB02TzySTEBGRXAIg=s48-c-k-c0x00ffffff-no-rj",
          "text": "Thank you for watching - that road earns every one of those curves.",
          "likeCount": 0,
          "publishedAt": "2026-07-21T16:18:59Z"
        }
      ]
    },
    {
      "id": "Ugyct15npxGUNDuuTkd4AaABAg",
      "author": "@saintedpatience",
      "authorImage": "https://yt3.ggpht.com/6C_gkfahAniv6XDVqfKA4E5DpsM23nOZMrhcweXxankC3mML_1F6Oix1VakSyojgupRtFg_BUDo=s48-c-k-c0x00ffffff-no-rj",
      "text": "I was going to tell you that all of this carbon footprint garbage paid off science crap was over with, and hoping that I was looking at an old video, but this is three weeks old and you're still spewing this garbage 🤮🤮🤮🤮🤮🤮🤮🤮🤮🤮🤮🤮",
      "likeCount": 1,
      "publishedAt": "2026-05-09T20:33:33Z",
      "replyCount": 0,
      "replies": []
    },
    {
      "id": "UgxBrL0BOph3eItFGap4AaABAg",
      "author": "@lubavukadinovic5752",
      "authorImage": "https://yt3.ggpht.com/ytc/AIdro_l5S4Bm8ys5rU_yXLwJGwmi61BHysn4WSwNjpbkuBE=s48-c-k-c0x00ffffff-no-rj",
      "text": "❤ 🙏👍 💯👍 from Toronto. FASCINATING, unknown",
      "likeCount": 1,
      "publishedAt": "2026-05-09T13:04:16Z",
      "replyCount": 0,
      "replies": []
    },
    {
      "id": "Ugzuca3Ht_1pVc4J88V4AaABAg",
      "author": "@jamess2834",
      "authorImage": "https://yt3.ggpht.com/ytc/AIdro_nYAelJ0EcVxM7GxOq8o_Z9NcH-71r3AQoGxCwTD_vhjrae=s48-c-k-c0x00ffffff-no-rj",
      "text": "I found your author's name on YouTube and I'm going to listen to the audiobook and I am going to include his name in my novel as one of my characters names",
      "likeCount": 2,
      "publishedAt": "2026-05-09T02:32:31Z",
      "replyCount": 2,
      "replies": [
        {
          "id": "Ugzuca3Ht_1pVc4J88V4AaABAg.AWZzddIIu2DAZXRKxXWD0j",
          "author": "@WhereonEarth4K",
          "authorImage": "https://yt3.ggpht.com/eGYI9iH4DF7Eb8QJYMMO2qNL_ls-4aNbWgY0tHLbCMrP4phySA3gN8SnhWB02TzySTEBGRXAIg=s48-c-k-c0x00ffffff-no-rj",
          "text": "That's a fun way to carry this forward - hope the character does the name justice.",
          "likeCount": 0,
          "publishedAt": "2026-07-21T16:19:42Z"
        },
        {
          "id": "Ugzuca3Ht_1pVc4J88V4AaABAg.AWZzddIIu2DAXFsY2nCfIL",
          "author": "@lovejackson2830",
          "authorImage": "https://yt3.ggpht.com/ytc/AIdro_lfu4Xfu4SF_0yI7A0venOHm2QTCx_-6hqMu0a-9MNDWJE=s48-c-k-c0x00ffffff-no-rj",
          "text": "Now I'm invested from your two posts. What is the name of your book?  It is very nice of you to name a character after this author.  That is very sweet and helps me know there are still good grateful people.",
          "likeCount": 0,
          "publishedAt": "2026-05-26T03:37:02Z"
        }
      ]
    },
    {
      "id": "UgzM99DpJUGWunrNmqd4AaABAg",
      "author": "@jamess2834",
      "authorImage": "https://yt3.ggpht.com/ytc/AIdro_nYAelJ0EcVxM7GxOq8o_Z9NcH-71r3AQoGxCwTD_vhjrae=s48-c-k-c0x00ffffff-no-rj",
      "text": "You have a very poetic way of speaking",
      "likeCount": 1,
      "publishedAt": "2026-05-09T02:11:32Z",
      "replyCount": 1,
      "replies": [
        {
          "id": "UgzM99DpJUGWunrNmqd4AaABAg.AWZxEy4qXESAZXRErYdJ3N",
          "author": "@WhereonEarth4K",
          "authorImage": "https://yt3.ggpht.com/eGYI9iH4DF7Eb8QJYMMO2qNL_ls-4aNbWgY0tHLbCMrP4phySA3gN8SnhWB02TzySTEBGRXAIg=s48-c-k-c0x00ffffff-no-rj",
          "text": "Thank you - glad it landed that way.",
          "likeCount": 0,
          "publishedAt": "2026-07-21T16:18:52Z"
        }
      ]
    },
    {
      "id": "UgxUsEbCvQ2VTNoeNEx4AaABAg",
      "author": "@jamess2834",
      "authorImage": "https://yt3.ggpht.com/ytc/AIdro_nYAelJ0EcVxM7GxOq8o_Z9NcH-71r3AQoGxCwTD_vhjrae=s48-c-k-c0x00ffffff-no-rj",
      "text": "And these are the cultures this is one of them that Vladimir Putin wants to absorb so that he can be remembered as the person who rebuilt Russia by taking over all of its neighbors",
      "likeCount": 2,
      "publishedAt": "2026-05-09T02:03:17Z",
      "replyCount": 2,
      "replies": [
        {
          "id": "UgxUsEbCvQ2VTNoeNEx4AaABAg.AWZwIW1tPeBAXDLG5_bM8O",
          "author": "@LindaCooper-i3f",
          "authorImage": "https://yt3.ggpht.com/ytc/AIdro_lDSJSDjAUAtuef0JTtAFXzaAujtvgNy8NZpTO3bv855fKQsLRkeAc5pd5228DEub_8fA=s48-c-k-c0x00ffffff-no-rj",
          "text": "Putin is both a mad man and a modern day LENIN!",
          "likeCount": 1,
          "publishedAt": "2026-05-25T03:59:01Z"
        },
        {
          "id": "UgxUsEbCvQ2VTNoeNEx4AaABAg.AWZwIW1tPeBAWtxIYSijTy",
          "author": "@Amsterdam020xx",
          "authorImage": "https://yt3.ggpht.com/ZrKe2UajQV7RssrD53pCN_DTxG2SSU-BKyD_0UePTERETvOWUuIoj6eIkl-TkPjueTbnd3ZsDg=s48-c-k-c0x00ffffff-no-rj",
          "text": "U not wrong u know 😢",
          "likeCount": 0,
          "publishedAt": "2026-05-17T05:56:05Z"
        }
      ]
    },
    {
      "id": "UgwS0YdLJY03PaohS214AaABAg",
      "author": "@jamess2834",
      "authorImage": "https://yt3.ggpht.com/ytc/AIdro_nYAelJ0EcVxM7GxOq8o_Z9NcH-71r3AQoGxCwTD_vhjrae=s48-c-k-c0x00ffffff-no-rj",
      "text": "Has a comment King Charles did this wonderful thing helping Transylvania and Mark Zuckerberg who owns Facebook bought one big chunk of Hawaii that the Hawaiian people hate and built a mention there it kind of says something about King Charles and Transylvania and Zuckerberg and Hawaii I think King Charles Transylvania and Hawaii come out on top and Zuckerberg is just not so much😊",
      "likeCount": 0,
      "publishedAt": "2026-05-09T01:40:14Z",
      "replyCount": 0,
      "replies": []
    },
    {
      "id": "Ugzn5DAv5H-xsp_SIwx4AaABAg",
      "author": "@jamess2834",
      "authorImage": "https://yt3.ggpht.com/ytc/AIdro_nYAelJ0EcVxM7GxOq8o_Z9NcH-71r3AQoGxCwTD_vhjrae=s48-c-k-c0x00ffffff-no-rj",
      "text": "My that is a bad guy is obsessed with finding electrum which is mined in the mountains thank you thank you thank you",
      "likeCount": 0,
      "publishedAt": "2026-05-09T01:22:23Z",
      "replyCount": 0,
      "replies": []
    },
    {
      "id": "Ugyk6xZbIATCBbNO0u14AaABAg",
      "author": "@jamess2834",
      "authorImage": "https://yt3.ggpht.com/ytc/AIdro_nYAelJ0EcVxM7GxOq8o_Z9NcH-71r3AQoGxCwTD_vhjrae=s48-c-k-c0x00ffffff-no-rj",
      "text": "I have learned a lot from your video I have a character who is a private detective and is a world traveler and I am going to include some of this information in one of his chapters thank you it will be published in about a month and a half and I will change a few sentences in the galleys thank you thank you thank you",
      "likeCount": 7,
      "publishedAt": "2026-05-09T01:06:16Z",
      "replyCount": 1,
      "replies": [
        {
          "id": "Ugyk6xZbIATCBbNO0u14AaABAg.AWZpltDE49IAYMoU7URIQV",
          "author": "@WhereonEarth4K",
          "authorImage": "https://yt3.ggpht.com/eGYI9iH4DF7Eb8QJYMMO2qNL_ls-4aNbWgY0tHLbCMrP4phySA3gN8SnhWB02TzySTEBGRXAIg=s48-c-k-c0x00ffffff-no-rj",
          "text": "A world-traveling private detective with a chapter in Transylvania might be the best use of a documentary we've heard. Hope the chapter finds what it's looking for. 🙏",
          "likeCount": 0,
          "publishedAt": "2026-06-22T16:47:38Z"
        }
      ]
    },
    {
      "id": "UgyQFHmdG1bnLH82-UV4AaABAg",
      "author": "@QuBoadicea69",
      "authorImage": "https://yt3.ggpht.com/ytc/AIdro_lE0kkoKv0FUpNf8VNpKT3e9RJxlW-V6DYonX_T2wVvD9A=s48-c-k-c0x00ffffff-no-rj",
      "text": "This is an astonishing creation and a pleasure to watch! I subscribe heartily and am glad to hear you use the terminology “before Christ” instead of BCE; that alone gets my vote for your excellent channel.  The only thing that would’ve made it absolutely perfect of course would be using a human voice, although you can barely tell. Well done in every way!",
      "likeCount": 7,
      "publishedAt": "2026-05-08T17:23:48Z",
      "replyCount": 1,
      "replies": [
        {
          "id": "UgyQFHmdG1bnLH82-UV4AaABAg.AWZ-qfPNQkbAWZI_VGyKoZ",
          "author": "@WhereonEarth4K",
          "authorImage": "https://yt3.ggpht.com/eGYI9iH4DF7Eb8QJYMMO2qNL_ls-4aNbWgY0tHLbCMrP4phySA3gN8SnhWB02TzySTEBGRXAIg=s48-c-k-c0x00ffffff-no-rj",
          "text": "Thank you for the warm welcome and for subscribing. The \"before Christ\" choice was deliberate... it felt right for the tone of these documentaries, and it's good to know that landed. The narration is something we're always refining, and we appreciate the feedback. Glad it resonated.",
          "likeCount": 2,
          "publishedAt": "2026-05-08T20:07:29Z"
        }
      ]
    },
    {
      "id": "UgwEKfiDkzWdpIV7cup4AaABAg",
      "author": "@Nicoleen-e1h",
      "authorImage": "https://yt3.ggpht.com/qYuGkcxBzkIgqsfDBedb_hgdcbIbmewpwNt1HIEdDLwhhjBS-5OJk5SpaNN5mq6-XuZtZMAu7g=s48-c-k-c0x00ffffff-no-rj",
      "text": "Thanks 😊",
      "likeCount": 4,
      "publishedAt": "2026-05-07T09:24:46Z",
      "replyCount": 1,
      "replies": [
        {
          "id": "UgwEKfiDkzWdpIV7cup4AaABAg.AWV_EBC2Td-AWWM1uDFW_p",
          "author": "@WhereonEarth4K",
          "authorImage": "https://yt3.ggpht.com/eGYI9iH4DF7Eb8QJYMMO2qNL_ls-4aNbWgY0tHLbCMrP4phySA3gN8SnhWB02TzySTEBGRXAIg=s48-c-k-c0x00ffffff-no-rj",
          "text": "My pleasure, thanks for watching! 😊",
          "likeCount": 0,
          "publishedAt": "2026-05-07T16:39:59Z"
        }
      ]
    },
    {
      "id": "UgxMgX8t4LR_PoVm6X54AaABAg",
      "author": "@daneaxe6465",
      "authorImage": "https://yt3.ggpht.com/ytc/AIdro_lQAQloWRviuvZXmH2Hlw7fGdEEweY6pwXhoYYiTWNLpQ=s48-c-k-c0x00ffffff-no-rj",
      "text": "25:06 The Round Churches on Bornholm island in Denmark are much older. The two round churches close to Hammershus fortress/castle were built in the 1050's. They are actually miniature fortresses with small church features built in the ground floor and weapons on the 2nd floor.",
      "likeCount": 3,
      "publishedAt": "2026-05-07T06:48:25Z",
      "replyCount": 1,
      "replies": [
        {
          "id": "UgxMgX8t4LR_PoVm6X54AaABAg.AWVIL7WocwvAZXRGTs4eD2",
          "author": "@WhereonEarth4K",
          "authorImage": "https://yt3.ggpht.com/eGYI9iH4DF7Eb8QJYMMO2qNL_ls-4aNbWgY0tHLbCMrP4phySA3gN8SnhWB02TzySTEBGRXAIg=s48-c-k-c0x00ffffff-no-rj",
          "text": "Great addition - the Bornholm round churches doubling as defensive structures with weapons on the second floor is a fascinating parallel. Appreciate the detail.",
          "likeCount": 0,
          "publishedAt": "2026-07-21T16:19:05Z"
        }
      ]
    },
    {
      "id": "Ugz3b3yaihQTW9g3Z2F4AaABAg",
      "author": "@Bmich1991",
      "authorImage": "https://yt3.ggpht.com/jdSXiCJIUfiI2L2-WQxNssrSkg_o0qGhKFleTxTVJSxb_LsU1JMXuyH3TGh3PkkbhZkJFiNizg=s48-c-k-c0x00ffffff-no-rj",
      "text": "I've lived in Romania for the last two years. I'm moving back to the states this year, but Romania will always hold a huge piece of my heart and I will certainly be back to visit, especially the parts of the country I have yet to experience.",
      "likeCount": 21,
      "publishedAt": "2026-05-06T11:31:03Z",
      "replyCount": 2,
      "replies": [
        {
          "id": "Ugz3b3yaihQTW9g3Z2F4AaABAg.AWTDtFsDFbWAZDOGRyggym",
          "author": "@rhondawentzell6959",
          "authorImage": "https://yt3.ggpht.com/7ZmYQtnBUBJMDNk7-nx0048SW6zJcHoaoVZvCLbfHbhfgMCZmlxA6lOy7PSilwXpWHfcg_uc=s48-c-k-c0x00ffffff-no-rj",
          "text": "WOW! That must’ve been amazing…a dream come true for me!",
          "likeCount": 0,
          "publishedAt": "2026-07-13T21:28:04Z"
        },
        {
          "id": "Ugz3b3yaihQTW9g3Z2F4AaABAg.AWTDtFsDFbWAWTMkVeEcSw",
          "author": "@WhereonEarth4K",
          "authorImage": "https://yt3.ggpht.com/eGYI9iH4DF7Eb8QJYMMO2qNL_ls-4aNbWgY0tHLbCMrP4phySA3gN8SnhWB02TzySTEBGRXAIg=s48-c-k-c0x00ffffff-no-rj",
          "text": "Two years is enough to understand what most visitors never get close to. The parts you haven't seen yet... especially the villages between the Saxon citadels and the Székely hills — are where Transylvania is most itself. Romania has a way of staying with people long after they leave.",
          "likeCount": 8,
          "publishedAt": "2026-05-06T12:48:30Z"
        }
      ]
    },
    {
      "id": "UgzpKzgo8kNqgmIcklF4AaABAg",
      "author": "@chrismcpherson1586",
      "authorImage": "https://yt3.ggpht.com/ytc/AIdro_kr4bNGofmTMPp5MZXDPMJK5LVxode4q5XfL_KkDT6k-92DsDa2ZJkQL47K5Z7lphmMUw=s48-c-k-c0x00ffffff-no-rj",
      "text": "Pennsylvania USA 🇺🇸   Transylvania is beautiful. I own our great great grandparents estate agent there. I actually was their filming 5 OnlyFans vidios over 10 days. Yes OnlyFans.  Im 24 yr old man The Transylvania mountain men are well built I have done 25 OnlyFans collabs with the men of Transylvania. The men don't ManScape. I have a guy who stays at my inherited estate all yr round. The home has 1 massive fireplace  im talking huge and 3 normal size fireplaces. The home is beautiful.  It gets so cold at the mountain home. Wildlife is so beautiful along with nature.  The people are nice.well the one's I have met. When the community found out I have a OnlyFans they were fascinated. I have met several families and I love the rural mountain people and the community.  A couple winters ago my first winter visit a Winter storm hit. 2024 I have never seen so much snow.  I was very well stocked.  A family about 5 miles away sent their oldest so to come and stay to help me learn how to get through such a expected big snow event.  He stayed 5 days. He was 2 yrs older than me. I already had enough split wood for 3 yrs. My great great grandparents home was built in1798. It has 3 bedrooms  and a open loft it's completely renovated and all original features of the home was kept. I remember seeing a big bear for the first time. It's was big powerful movements and beautiful.  The area I live in  the rural are mostly bisexual from what I discovered.  The men have more stamina than American men. I love their black hair.its so shiny and it's so black their hair looks blue. I'm 26 miles from Draculas castle. As I said I only stay 6 weeks a yr.",
      "likeCount": 0,
      "publishedAt": "2026-05-06T01:37:20Z",
      "replyCount": 0,
      "replies": []
    },
    {
      "id": "UgwozbfL4u_3WcBFcxR4AaABAg",
      "author": "@LegacyCapri",
      "authorImage": "https://yt3.ggpht.com/GYLFTXmqKpMqEQyFfj3U-fMi4ZGqNrt5nxhdyyJZLJBt_CeVkJDL0uWgLNdAjtAUrQvcE2Twsg=s48-c-k-c0x00ffffff-no-rj",
      "text": "What a wonderful video!",
      "likeCount": 7,
      "publishedAt": "2026-05-05T18:32:59Z",
      "replyCount": 1,
      "replies": [
        {
          "id": "UgwozbfL4u_3WcBFcxR4AaABAg.AWRPNfrAd4dAWTMYm78H3Q",
          "author": "@WhereonEarth4K",
          "authorImage": "https://yt3.ggpht.com/eGYI9iH4DF7Eb8QJYMMO2qNL_ls-4aNbWgY0tHLbCMrP4phySA3gN8SnhWB02TzySTEBGRXAIg=s48-c-k-c0x00ffffff-no-rj",
          "text": "Thank you for watching, glad you enjoyed the journey!",
          "likeCount": 1,
          "publishedAt": "2026-05-06T12:46:45Z"
        }
      ]
    },
    {
      "id": "Ugx_hgiYZZ8L-Tr1Gsp4AaABAg",
      "author": "@suze816",
      "authorImage": "https://yt3.ggpht.com/ytc/AIdro_nAfBcFU5j5GiNwMl4gtCXOgTfI5K74v_KBXW7DQ04=s48-c-k-c0x00ffffff-no-rj",
      "text": "Native Texan here.. Thank you for this fascinating video ! ❤.. I knew a bit about the real Vlad Tepes/Dracul and knew he was a hero to his country..\nBut there is SO much more to Transylvania than that.. \nI'm happy to know that King Charles has had the  interest he's had and contributed So Much.. \nHow cool to discover one's ancestor was ole Vlad !! 😊",
      "likeCount": 15,
      "publishedAt": "2026-05-05T17:46:08Z",
      "replyCount": 1,
      "replies": [
        {
          "id": "Ugx_hgiYZZ8L-Tr1Gsp4AaABAg.AWRK0ejSx01AWTMmW9WRyh",
          "author": "@WhereonEarth4K",
          "authorImage": "https://yt3.ggpht.com/eGYI9iH4DF7Eb8QJYMMO2qNL_ls-4aNbWgY0tHLbCMrP4phySA3gN8SnhWB02TzySTEBGRXAIg=s48-c-k-c0x00ffffff-no-rj",
          "text": "That reaction is exactly why we made this. Most people start with Vlad and stop there... but the real Transylvania runs so much deeper than the one figure the world fixated on. The fact that a British king kept coming back for 25 years, not for the fame but for the quietness, says everything about what's actually there. Glad it resonated all the way from Texas.",
          "likeCount": 3,
          "publishedAt": "2026-05-06T12:48:46Z"
        }
      ]
    },
    {
      "id": "UgxrQsPiSzGuY5vo1pt4AaABAg",
      "author": "@TashminNur",
      "authorImage": "https://yt3.ggpht.com/6zgwhVWVu3Sq3zxe181wR_KJg-7339-tHt0J7aA32PkW42E4N2Ge_iX4SYtV0kYg6JXw9o9P=s48-c-k-c0x00ffffff-no-rj",
      "text": "Is that the castle where Count Dracula lives?",
      "likeCount": 2,
      "publishedAt": "2026-05-05T17:45:45Z",
      "replyCount": 4,
      "replies": [
        {
          "id": "UgxrQsPiSzGuY5vo1pt4AaABAg.AWRJyoVHhRNAXGnOaLVZob",
          "author": "@TCGaming4fun",
          "authorImage": "https://yt3.ggpht.com/9qDOxuJOmKBSeeGflVQ2D5a7bCWS1ZMBRb2JddKmcGDKA17FXVHkxI_QDWi6lc7RF3dTvJSDUA=s48-c-k-c0x00ffffff-no-rj",
          "text": "​ @TashminNur  Not really.🤨",
          "likeCount": 0,
          "publishedAt": "2026-05-26T12:11:18Z"
        },
        {
          "id": "UgxrQsPiSzGuY5vo1pt4AaABAg.AWRJyoVHhRNAXGnNwa50Sj",
          "author": "@TCGaming4fun",
          "authorImage": "https://yt3.ggpht.com/9qDOxuJOmKBSeeGflVQ2D5a7bCWS1ZMBRb2JddKmcGDKA17FXVHkxI_QDWi6lc7RF3dTvJSDUA=s48-c-k-c0x00ffffff-no-rj",
          "text": "​@TashminNur Not really.🤨",
          "likeCount": 0,
          "publishedAt": "2026-05-26T12:11:13Z"
        },
        {
          "id": "UgxrQsPiSzGuY5vo1pt4AaABAg.AWRJyoVHhRNAWTNoXSJaib",
          "author": "@TashminNur",
          "authorImage": "https://yt3.ggpht.com/6zgwhVWVu3Sq3zxe181wR_KJg-7339-tHt0J7aA32PkW42E4N2Ge_iX4SYtV0kYg6JXw9o9P=s48-c-k-c0x00ffffff-no-rj",
          "text": "​@WhereonEarth4KOh,, thank you so much. My comment was actually fun 😊.",
          "likeCount": 0,
          "publishedAt": "2026-05-06T12:57:47Z"
        },
        {
          "id": "UgxrQsPiSzGuY5vo1pt4AaABAg.AWRJyoVHhRNAWTMpdKY2Rf",
          "author": "@WhereonEarth4K",
          "authorImage": "https://yt3.ggpht.com/eGYI9iH4DF7Eb8QJYMMO2qNL_ls-4aNbWgY0tHLbCMrP4phySA3gN8SnhWB02TzySTEBGRXAIg=s48-c-k-c0x00ffffff-no-rj",
          "text": "That's exactly the question this documentary answers. The short version: Count Dracula is a fictional character from an 1897 novel written by a man who never visited Romania. The castle the world calls \"Dracula's Castle\" — Bran Castle... has almost no connection to the real Vlad III. His actual fortress was Poenari, 750 kilometers away. The full story is in the video... it's stranger than the fiction.",
          "likeCount": 1,
          "publishedAt": "2026-05-06T12:49:12Z"
        }
      ]
    },
    {
      "id": "Ugz_KJPFRqWzziSwoVN4AaABAg",
      "author": "@torbergman6977",
      "authorImage": "https://yt3.ggpht.com/ytc/AIdro_nSY3SKVIB-lh59yGyZKnSBMStdyKAx-ey6Y__AoaVIck-hLXmMGqnd_XiRQfZveTs5Jg=s48-c-k-c0x00ffffff-no-rj",
      "text": "Starts by criticizing stereotype than continues to promote it 😂👎 The Carpathians stretch through Central and Southeastern Europe, NOT Eastern! Second, the mountains are crossed by way more than just the two tourist roads mentioned here as closed during winter. Third, showing a lot of images that are not from the place mentioned. And I could go on and completely destroy this! \nClearly this is some hotchpotch AI made by someone who randomly took photos and clip fragments from the internet!",
      "likeCount": 2,
      "publishedAt": "2026-05-03T11:57:40Z",
      "replyCount": 0,
      "replies": []
    },
    {
      "id": "UgyByVXUUc65oCDfa-Z4AaABAg",
      "author": "@jasonk795",
      "authorImage": "https://yt3.ggpht.com/xJa5x2CDZ-odFJGUD6wngZLjBirSFVRcjsMALnN2FqCLfr9WdwjAKm40prsNVtAoTthkXIE0=s48-c-k-c0x00ffffff-no-rj",
      "text": "2:14 looks like firecracker smoke.",
      "likeCount": 2,
      "publishedAt": "2026-05-03T07:37:51Z",
      "replyCount": 1,
      "replies": [
        {
          "id": "UgyByVXUUc65oCDfa-Z4AaABAg.AWL4ohtElBYAZXRHZU1m3C",
          "author": "@WhereonEarth4K",
          "authorImage": "https://yt3.ggpht.com/eGYI9iH4DF7Eb8QJYMMO2qNL_ls-4aNbWgY0tHLbCMrP4phySA3gN8SnhWB02TzySTEBGRXAIg=s48-c-k-c0x00ffffff-no-rj",
          "text": "Good eye - worth double-checking that shot to confirm what's actually being shown there.",
          "likeCount": 0,
          "publishedAt": "2026-07-21T16:19:14Z"
        }
      ]
    },
    {
      "id": "Ugz1uUuFIcOf8Lae5z14AaABAg",
      "author": "@tonycoburn4153",
      "authorImage": "https://yt3.ggpht.com/ytc/AIdro_mK6yEs8PVWeq_qBBd11txe8zCDy-DAaLGimzbHA1w=s48-c-k-c0x00ffffff-no-rj",
      "text": "There wouldnt be 140 bears gathered together at one time?  Either something/s took the bears into the cave or generation's of bear inhabited this cave\n I dont think 140 bears were hanging out in this cave and suddenly become trapped  leaving fossils 40,000 years later for us to find.\nPersonally cave man had a taste for bear  brought them in 1 or 2 at a time  leaving the skeletons behind to become fossils  and now star in this film.",
      "likeCount": 3,
      "publishedAt": "2026-05-02T02:03:16Z",
      "replyCount": 1,
      "replies": [
        {
          "id": "Ugz1uUuFIcOf8Lae5z14AaABAg.AWHujCs2EHnAWI18cwsgSM",
          "author": "@WhereonEarth4K",
          "authorImage": "https://yt3.ggpht.com/eGYI9iH4DF7Eb8QJYMMO2qNL_ls-4aNbWgY0tHLbCMrP4phySA3gN8SnhWB02TzySTEBGRXAIg=s48-c-k-c0x00ffffff-no-rj",
          "text": "You're thinking about it the right way. The Peștera cu Oase fossils accumulated over thousands of years... generations of cave bears using the same cave system for hibernation, not one gathering. The bones built up layer by layer across millennia. It's the timescale that makes it extraordinary.",
          "likeCount": 0,
          "publishedAt": "2026-05-02T03:08:02Z"
        }
      ]
    },
    {
      "id": "UgxcXTQ4CGM1mpz-Y5d4AaABAg",
      "author": "@AlexSVELES-c3f",
      "authorImage": "https://yt3.ggpht.com/ytc/AIdro_meYAh6NPkc3qZ9RQbztfozX2jknUqc69hcasQTLZa7CCWY6MHmzRI1I6I59gYFhEiQXA=s48-c-k-c0x00ffffff-no-rj",
      "text": "Transylvania is definitely not where vampirw originate.\nUkra7ne is",
      "likeCount": 1,
      "publishedAt": "2026-05-02T00:06:36Z",
      "replyCount": 3,
      "replies": [
        {
          "id": "UgxcXTQ4CGM1mpz-Y5d4AaABAg.AWHhNh7T4gZAWK0D1zMWAz",
          "author": "@crc-d7s",
          "authorImage": "https://yt3.ggpht.com/ytc/AIdro_mcQV1blZZGdTiUX4cVsdf4Vy1SlQ-i1uoE3AVa33Ptbpk4q41f12BxxTp0ggs_2KzTew=s48-c-k-c0x00ffffff-no-rj",
          "text": "@WhereonEarth4K the connection is thicker than most people assume. Vampires drink blood because Bram Stoker took the fact that Vlad the Impaler was always depicted as drinking blood, by the Transylvanian Saxons. Bram Stoker also took a Romanian tradition which says that during the Saint Andrew's night, all ghosts and monsters come out and people need to put garlic at the windows and doors. That's why we have today that vampires hate garlic. Etc.",
          "likeCount": 0,
          "publishedAt": "2026-05-02T21:38:23Z"
        },
        {
          "id": "UgxcXTQ4CGM1mpz-Y5d4AaABAg.AWHhNh7T4gZAWI1EOh6vjq",
          "author": "@WhereonEarth4K",
          "authorImage": "https://yt3.ggpht.com/eGYI9iH4DF7Eb8QJYMMO2qNL_ls-4aNbWgY0tHLbCMrP4phySA3gN8SnhWB02TzySTEBGRXAIg=s48-c-k-c0x00ffffff-no-rj",
          "text": "Vampire folklore does have deep roots across Eastern Europe.... Romania, Serbia, Greece, and yes, parts of what is now Ukraine all have their own traditions. What made Transylvania synonymous with vampires specifically was Bram Stoker's 1897 novel, which borrowed the name and the atmosphere but had very little to do with actual Romanian folklore. The real connection is thinner than most people assume.",
          "likeCount": 0,
          "publishedAt": "2026-05-02T03:08:49Z"
        },
        {
          "id": "UgxcXTQ4CGM1mpz-Y5d4AaABAg.AWHhNh7T4gZAWHjf4IQRLN",
          "author": "@aimieward6298",
          "authorImage": "https://yt3.ggpht.com/ytc/AIdro_niHAflZLrcpSo8Bgp11F1bWBq4Tq76_iFw7LjBg54=s48-c-k-c0x00ffffff-no-rj",
          "text": "Vampire mythology exists all throughout history, all over the world.",
          "likeCount": 2,
          "publishedAt": "2026-05-02T00:26:35Z"
        }
      ]
    },
    {
      "id": "UgyLk-5oUmSlJg8te3V4AaABAg",
      "author": "@davehansen6112",
      "authorImage": "https://yt3.ggpht.com/ytc/AIdro_mBVNsGOPmaU5A11ntmIeNgKYqCDoujcui9IgUTGH76DIMXsWCfsYP1u5nTgQTXotUAtA=s48-c-k-c0x00ffffff-no-rj",
      "text": "There was no mention of the ancient Jewish community...I wish there had been.  Wonderful production though.",
      "likeCount": 6,
      "publishedAt": "2026-05-01T00:53:57Z",
      "replyCount": 1,
      "replies": [
        {
          "id": "UgyLk-5oUmSlJg8te3V4AaABAg.AWFD-eF9Wd8AWI1A66FgbN",
          "author": "@WhereonEarth4K",
          "authorImage": "https://yt3.ggpht.com/eGYI9iH4DF7Eb8QJYMMO2qNL_ls-4aNbWgY0tHLbCMrP4phySA3gN8SnhWB02TzySTEBGRXAIg=s48-c-k-c0x00ffffff-no-rj",
          "text": "That's a fair point, and it's a story that deserves its own depth.... the Jewish communities of Transylvania, especially in cities like Cluj and Sighișoara, were a significant part of the region's cultural fabric. At 72 minutes we had to make difficult choices about what to include, but it's a thread we'd love to explore further. Thank you for watching.",
          "likeCount": 1,
          "publishedAt": "2026-05-02T03:08:14Z"
        }
      ]
    },
    {
      "id": "UgyQOHlLeu4S8ADVsvt4AaABAg",
      "author": "@JerrySponagle-f7s",
      "authorImage": "https://yt3.ggpht.com/ytc/AIdro_nkHMdD8-iph0EM_9XXOHFTX5yr1_08Pyl5RsRmTC8NcKJnWauEhfigEgk72JRwumN-OA=s48-c-k-c0x00ffffff-no-rj",
      "text": "I am from Nova Scotia, Canada. I would love to visit this wildnerness.",
      "likeCount": 9,
      "publishedAt": "2026-04-30T20:58:05Z",
      "replyCount": 2,
      "replies": [
        {
          "id": "UgyQOHlLeu4S8ADVsvt4AaABAg.AWEn07FE2pzAXDJwH6zu24",
          "author": "@LindaCooper-i3f",
          "authorImage": "https://yt3.ggpht.com/ytc/AIdro_lDSJSDjAUAtuef0JTtAFXzaAujtvgNy8NZpTO3bv855fKQsLRkeAc5pd5228DEub_8fA=s48-c-k-c0x00ffffff-no-rj",
          "text": "I grew up in the hills of eastern Kentucky, so the Carphatians should be no different from The Appalachians!",
          "likeCount": 1,
          "publishedAt": "2026-05-25T03:47:26Z"
        },
        {
          "id": "UgyQOHlLeu4S8ADVsvt4AaABAg.AWEn07FE2pzAWI170o4u3B",
          "author": "@WhereonEarth4K",
          "authorImage": "https://yt3.ggpht.com/eGYI9iH4DF7Eb8QJYMMO2qNL_ls-4aNbWgY0tHLbCMrP4phySA3gN8SnhWB02TzySTEBGRXAIg=s48-c-k-c0x00ffffff-no-rj",
          "text": "It's worth the trip. The Carpathians feel like what the rest of Europe must have looked like centuries ago... except it's still there, still functioning. If you make it, start in the villages between Sibiu and Brașov. That stretch is the heart of everything we covered. 🌲",
          "likeCount": 4,
          "publishedAt": "2026-05-02T03:07:49Z"
        }
      ]
    },
    {
      "id": "Ugx-51mUIFP_ZonTaER4AaABAg",
      "author": "@JerrySponagle-f7s",
      "authorImage": "https://yt3.ggpht.com/ytc/AIdro_nkHMdD8-iph0EM_9XXOHFTX5yr1_08Pyl5RsRmTC8NcKJnWauEhfigEgk72JRwumN-OA=s48-c-k-c0x00ffffff-no-rj",
      "text": "Romania could use some cougar or mountain lion .",
      "likeCount": 2,
      "publishedAt": "2026-04-30T20:57:32Z",
      "replyCount": 3,
      "replies": [
        {
          "id": "Ugx-51mUIFP_ZonTaER4AaABAg.AWEmx9cl7OIAXDKk88VVvI",
          "author": "@LindaCooper-i3f",
          "authorImage": "https://yt3.ggpht.com/ytc/AIdro_lDSJSDjAUAtuef0JTtAFXzaAujtvgNy8NZpTO3bv855fKQsLRkeAc5pd5228DEub_8fA=s48-c-k-c0x00ffffff-no-rj",
          "text": "They could possibly use some BigHorn sheep from both Montana and Canada!",
          "likeCount": 1,
          "publishedAt": "2026-05-25T03:54:31Z"
        },
        {
          "id": "Ugx-51mUIFP_ZonTaER4AaABAg.AWEmx9cl7OIAXDKdt7gupX",
          "author": "@LindaCooper-i3f",
          "authorImage": "https://yt3.ggpht.com/ytc/AIdro_lDSJSDjAUAtuef0JTtAFXzaAujtvgNy8NZpTO3bv855fKQsLRkeAc5pd5228DEub_8fA=s48-c-k-c0x00ffffff-no-rj",
          "text": "The European Bison would give them a run for their Kopeks!",
          "likeCount": 1,
          "publishedAt": "2026-05-25T03:53:39Z"
        },
        {
          "id": "Ugx-51mUIFP_ZonTaER4AaABAg.AWEmx9cl7OIAWI1_GOX3V7",
          "author": "@WhereonEarth4K",
          "authorImage": "https://yt3.ggpht.com/eGYI9iH4DF7Eb8QJYMMO2qNL_ls-4aNbWgY0tHLbCMrP4phySA3gN8SnhWB02TzySTEBGRXAIg=s48-c-k-c0x00ffffff-no-rj",
          "text": "Romania's already got brown bears, wolves, lynx, and recently reintroduced bison...the Carpathians are the most predator-dense mountain range in Europe outside of Scandinavia. They're doing alright on the large carnivore front 🐻",
          "likeCount": 1,
          "publishedAt": "2026-05-02T03:11:49Z"
        }
      ]
    },
    {
      "id": "UgzEBSxs01LQs3-h3ex4AaABAg",
      "author": "@LindaCooper-i3f",
      "authorImage": "https://yt3.ggpht.com/ytc/AIdro_lDSJSDjAUAtuef0JTtAFXzaAujtvgNy8NZpTO3bv855fKQsLRkeAc5pd5228DEub_8fA=s48-c-k-c0x00ffffff-no-rj",
      "text": "@WhereonEarth4K, \nMy ex-husband and oldest son are both descendants of Vlad III aka Vlad The Impaler, and they’re proud of it.",
      "likeCount": 1,
      "publishedAt": "2026-04-30T01:01:02Z",
      "replyCount": 2,
      "replies": [
        {
          "id": "UgzEBSxs01LQs3-h3ex4AaABAg.AWCe0irlBRsAXDIeTbZ0HK",
          "author": "@LindaCooper-i3f",
          "authorImage": "https://yt3.ggpht.com/ytc/AIdro_lDSJSDjAUAtuef0JTtAFXzaAujtvgNy8NZpTO3bv855fKQsLRkeAc5pd5228DEub_8fA=s48-c-k-c0x00ffffff-no-rj",
          "text": "Oh believe me, they’re proud of how he defended all of greater Christendom from the Ottomans! \nIn fact, my late brother-in-law Gilbert Wilson Cooper (1953-1984), was the carbon copy image of Vlad! \nAfterall, my ex-brother-in-law Daniel Boone Cooper is the carbon copy image of Tsar Peter I aka Peter The Great of Russia while my ex-brother-in-law Tommy Cooper is the very carbon copy image of Grand Prince Vladimir of Kiev, and my late brother-in-law Jimmy Cooper (who passed away at 13 from leukemia) was the carbon copy image of Tsar Alexander I!",
          "likeCount": 1,
          "publishedAt": "2026-05-25T03:36:16Z"
        },
        {
          "id": "UgzEBSxs01LQs3-h3ex4AaABAg.AWCe0irlBRsAWI1Y6J0oMZ",
          "author": "@WhereonEarth4K",
          "authorImage": "https://yt3.ggpht.com/eGYI9iH4DF7Eb8QJYMMO2qNL_ls-4aNbWgY0tHLbCMrP4phySA3gN8SnhWB02TzySTEBGRXAIg=s48-c-k-c0x00ffffff-no-rj",
          "text": "That's quite a family tree. In Romania, Vlad is remembered very differently than the rest of the world imagines him... a defender, not a monster. They should be proud of that lineage.",
          "likeCount": 1,
          "publishedAt": "2026-05-02T03:11:31Z"
        }
      ]
    },
    {
      "id": "Ugwv6zova_42OvW3gDB4AaABAg",
      "author": "@Corry-i4t",
      "authorImage": "https://yt3.ggpht.com/ytc/AIdro_mFmMDykxr3lGz5FWRvWHgznFmrUUjvmzl9ImuK4gVddDF3sBeW9RiP3Nomuh8l0FF0CA=s48-c-k-c0x00ffffff-no-rj",
      "text": "I live in Pennsylvania, where all the gouls and dieties retired to.  It's nicer here. Hey internet tell them we said hi.",
      "likeCount": 2,
      "publishedAt": "2026-04-29T23:45:24Z",
      "replyCount": 3,
      "replies": [
        {
          "id": "Ugwv6zova_42OvW3gDB4AaABAg.AWCWMdChmAFAXDLzyux06E",
          "author": "@LindaCooper-i3f",
          "authorImage": "https://yt3.ggpht.com/ytc/AIdro_lDSJSDjAUAtuef0JTtAFXzaAujtvgNy8NZpTO3bv855fKQsLRkeAc5pd5228DEub_8fA=s48-c-k-c0x00ffffff-no-rj",
          "text": "“Heavens to hemlock!”,\nCharles Addams.",
          "likeCount": 1,
          "publishedAt": "2026-05-25T04:05:25Z"
        },
        {
          "id": "Ugwv6zova_42OvW3gDB4AaABAg.AWCWMdChmAFAWI1RR1Nf_V",
          "author": "@WhereonEarth4K",
          "authorImage": "https://yt3.ggpht.com/eGYI9iH4DF7Eb8QJYMMO2qNL_ls-4aNbWgY0tHLbCMrP4phySA3gN8SnhWB02TzySTEBGRXAIg=s48-c-k-c0x00ffffff-no-rj",
          "text": "Pennsylvania: where Transylvania's retirees go when they want better weather and less impaling. Hi back from the internet 👋",
          "likeCount": 1,
          "publishedAt": "2026-05-02T03:10:36Z"
        },
        {
          "id": "Ugwv6zova_42OvW3gDB4AaABAg.AWCWMdChmAFAWCdUUdPwjH",
          "author": "@LindaCooper-i3f",
          "authorImage": "https://yt3.ggpht.com/ytc/AIdro_lDSJSDjAUAtuef0JTtAFXzaAujtvgNy8NZpTO3bv855fKQsLRkeAc5pd5228DEub_8fA=s48-c-k-c0x00ffffff-no-rj",
          "text": "“Great shades of Hades!”,\nGomez Addams.",
          "likeCount": 1,
          "publishedAt": "2026-04-30T00:56:22Z"
        }
      ]
    },
    {
      "id": "UgxVqxmotfcIuwjfb6J4AaABAg",
      "author": "@erikatordai389",
      "authorImage": "https://yt3.ggpht.com/ytc/AIdro_kM-WAu7FWM5pmrrS2-NC8y_6-_YVvoqsqAUPMGai-iELDBMp6AMgTDLNobZjJ49rXWmQ=s48-c-k-c0x00ffffff-no-rj",
      "text": "OCHII  SIBIULUI❤😊",
      "likeCount": 1,
      "publishedAt": "2026-04-29T16:13:39Z",
      "replyCount": 4,
      "replies": [
        {
          "id": "UgxVqxmotfcIuwjfb6J4AaABAg.AWBhf-ub-ysAWI1PPcpjpt",
          "author": "@WhereonEarth4K",
          "authorImage": "https://yt3.ggpht.com/eGYI9iH4DF7Eb8QJYMMO2qNL_ls-4aNbWgY0tHLbCMrP4phySA3gN8SnhWB02TzySTEBGRXAIg=s48-c-k-c0x00ffffff-no-rj",
          "text": "The eyes of Sibiu... once you see them watching, you can't unsee them 👀",
          "likeCount": 0,
          "publishedAt": "2026-05-02T03:10:20Z"
        },
        {
          "id": "UgxVqxmotfcIuwjfb6J4AaABAg.AWBhf-ub-ysAWCfILfjQQX",
          "author": "@LindaCooper-i3f",
          "authorImage": "https://yt3.ggpht.com/ytc/AIdro_lDSJSDjAUAtuef0JTtAFXzaAujtvgNy8NZpTO3bv855fKQsLRkeAc5pd5228DEub_8fA=s48-c-k-c0x00ffffff-no-rj",
          "text": "In totally full agreement.",
          "likeCount": 1,
          "publishedAt": "2026-04-30T01:12:11Z"
        },
        {
          "id": "UgxVqxmotfcIuwjfb6J4AaABAg.AWBhf-ub-ysAWCfFneptna",
          "author": "@LindaCooper-i3f",
          "authorImage": "https://yt3.ggpht.com/ytc/AIdro_lDSJSDjAUAtuef0JTtAFXzaAujtvgNy8NZpTO3bv855fKQsLRkeAc5pd5228DEub_8fA=s48-c-k-c0x00ffffff-no-rj",
          "text": "Agree completely.",
          "likeCount": 1,
          "publishedAt": "2026-04-30T01:11:50Z"
        },
        {
          "id": "UgxVqxmotfcIuwjfb6J4AaABAg.AWBhf-ub-ysAWBitBiPNir",
          "author": "@erikatordai389",
          "authorImage": "https://yt3.ggpht.com/ytc/AIdro_kM-WAu7FWM5pmrrS2-NC8y_6-_YVvoqsqAUPMGai-iELDBMp6AMgTDLNobZjJ49rXWmQ=s48-c-k-c0x00ffffff-no-rj",
          "text": "MIHAI  EMINESCU😊",
          "likeCount": 0,
          "publishedAt": "2026-04-29T16:24:20Z"
        }
      ]
    },
    {
      "id": "UgztQNs9nZRIO6HfbDJ4AaABAg",
      "author": "@EpicEarthYTB",
      "authorImage": "https://yt3.ggpht.com/HVeo4ZS4uBGsjoC1_8ke1TjVRzOOXuwDxAxxO-4aZ-y2xzrz4LJctRUsE2xryhR4KwFulQ_r=s48-c-k-c0x00ffffff-no-rj",
      "text": "It’s fascinating to learn that the real Transylvania is far more captivating than the Dracula myth. This video beautifully showcases a land rich in history, diverse cultures, and untouched nature.",
      "likeCount": 28,
      "publishedAt": "2026-04-29T13:55:29Z",
      "replyCount": 2,
      "replies": [
        {
          "id": "UgztQNs9nZRIO6HfbDJ4AaABAg.AWBSr0niR-WAZXRIONoJcH",
          "author": "@WhereonEarth4K",
          "authorImage": "https://yt3.ggpht.com/eGYI9iH4DF7Eb8QJYMMO2qNL_ls-4aNbWgY0tHLbCMrP4phySA3gN8SnhWB02TzySTEBGRXAIg=s48-c-k-c0x00ffffff-no-rj",
          "text": "Thank you - that was exactly the perception gap we wanted to close.",
          "likeCount": 0,
          "publishedAt": "2026-07-21T16:19:21Z"
        },
        {
          "id": "UgztQNs9nZRIO6HfbDJ4AaABAg.AWBSr0niR-WAWCe3XoFgq0",
          "author": "@LindaCooper-i3f",
          "authorImage": "https://yt3.ggpht.com/ytc/AIdro_lDSJSDjAUAtuef0JTtAFXzaAujtvgNy8NZpTO3bv855fKQsLRkeAc5pd5228DEub_8fA=s48-c-k-c0x00ffffff-no-rj",
          "text": "Likewise.",
          "likeCount": 2,
          "publishedAt": "2026-04-30T01:01:25Z"
        }
      ]
    },
    {
      "id": "UgxapvyK4ZUXl31BhSN4AaABAg",
      "author": "@Luke-Skymaster",
      "authorImage": "https://yt3.ggpht.com/ytc/AIdro_kq2JMaYmMNo7ahz_HhVYGb9rKc9a3EEII73cX3aTsY41Q=s48-c-k-c0x00ffffff-no-rj",
      "text": "Mistake , they were more religions , the first orthodox church in Transilvania was Densuș Church from 13th century . You skipped the orthodox church",
      "likeCount": 6,
      "publishedAt": "2026-04-28T22:35:57Z",
      "replyCount": 3,
      "replies": [
        {
          "id": "UgxapvyK4ZUXl31BhSN4AaABAg.AW9oc5TQsG1AWI5fhCmSLX",
          "author": "@Luke-Skymaster",
          "authorImage": "https://yt3.ggpht.com/ytc/AIdro_kq2JMaYmMNo7ahz_HhVYGb9rKc9a3EEII73cX3aTsY41Q=s48-c-k-c0x00ffffff-no-rj",
          "text": "@WhereonEarth4K     That is the problem , it was no section whatsoever, you completely ignored it, you didn’t mention the orthodox church once.  Focusing on a racist Edict who didn’t even recognize Romanian minorities as present in Transilvania is not the smartest excuse. That was the reason Romanians went to the Pope and that’s how the Greco Catholic Romanian church came in existence, for the recognition . They were tired of being completely  ignored by the Hungarians and be counted as goods , like the sheep and cows.  Why you fail to mention how many Romanians live in Transilvania while counting 3 million poor Hungarians caught outside Hungary’s border ? That includes, Slovakia, Serbia , Ukraine and Romania , but not .. you let watchers imagine 3 millions Hungarians in Transilvania. No, they are 1 million vs 6 million Romanians.  Discret biased bs like any other British sticking his ignorant nose in Transilvania. You don’t start a world war and expect no consequences when losing  , after being a ruling minority in other people lands for centuries , tell the truth, not the doctored and romanticized bs",
          "likeCount": 2,
          "publishedAt": "2026-05-02T03:47:39Z"
        },
        {
          "id": "UgxapvyK4ZUXl31BhSN4AaABAg.AW9oc5TQsG1AWI1IsBR-26",
          "author": "@WhereonEarth4K",
          "authorImage": "https://yt3.ggpht.com/eGYI9iH4DF7Eb8QJYMMO2qNL_ls-4aNbWgY0tHLbCMrP4phySA3gN8SnhWB02TzySTEBGRXAIg=s48-c-k-c0x00ffffff-no-rj",
          "text": "Densus is remarkable.... one of the oldest stone churches in Romania, and built partly with materials from the Roman ruins at Sarmizegetusa. We focused the religious freedom section on the Edict of Torda and its four officially recognized denominations, and covered Orthodoxy through the Maramureș wooden churches and the suppression they faced under Habsburg rule. But you're right that the Orthodox tradition in Transylvania runs much deeper than any single section can capture.",
          "likeCount": 2,
          "publishedAt": "2026-05-02T03:09:26Z"
        },
        {
          "id": "UgxapvyK4ZUXl31BhSN4AaABAg.AW9oc5TQsG1AWCdQ1M3vwR",
          "author": "@LindaCooper-i3f",
          "authorImage": "https://yt3.ggpht.com/ytc/AIdro_lDSJSDjAUAtuef0JTtAFXzaAujtvgNy8NZpTO3bv855fKQsLRkeAc5pd5228DEub_8fA=s48-c-k-c0x00ffffff-no-rj",
          "text": "I understand completely.",
          "likeCount": 1,
          "publishedAt": "2026-04-30T00:55:45Z"
        }
      ]
    },
    {
      "id": "UgzfTjGDncQuKkG_sWp4AaABAg",
      "author": "@danielracovitan9779",
      "authorImage": "https://yt3.ggpht.com/ytc/AIdro_m7dVGLqWohJXZdPaUmRXdN6FBPwodlDuohwKt5mMX7hxI=s48-c-k-c0x00ffffff-no-rj",
      "text": "The \"forests areas lost\" is a LIE: today, Romania has 8% MORE forest area than it had in 1989 at the fall of Communism.",
      "likeCount": 7,
      "publishedAt": "2026-04-28T11:04:30Z",
      "replyCount": 5,
      "replies": [
        {
          "id": "UgzfTjGDncQuKkG_sWp4AaABAg.AW8_UsaPJQWAXDLu5jM1-U",
          "author": "@LindaCooper-i3f",
          "authorImage": "https://yt3.ggpht.com/ytc/AIdro_lDSJSDjAUAtuef0JTtAFXzaAujtvgNy8NZpTO3bv855fKQsLRkeAc5pd5228DEub_8fA=s48-c-k-c0x00ffffff-no-rj",
          "text": "Interesting point.",
          "likeCount": 1,
          "publishedAt": "2026-05-25T04:04:37Z"
        },
        {
          "id": "UgzfTjGDncQuKkG_sWp4AaABAg.AW8_UsaPJQWAXDLcYSN-s_",
          "author": "@LindaCooper-i3f",
          "authorImage": "https://yt3.ggpht.com/ytc/AIdro_lDSJSDjAUAtuef0JTtAFXzaAujtvgNy8NZpTO3bv855fKQsLRkeAc5pd5228DEub_8fA=s48-c-k-c0x00ffffff-no-rj",
          "text": "Then maybe we just need to clear away just enough for a railway right-of-way to link all isolated villages to the outside world?!?",
          "likeCount": 1,
          "publishedAt": "2026-05-25T04:02:13Z"
        },
        {
          "id": "UgzfTjGDncQuKkG_sWp4AaABAg.AW8_UsaPJQWAWI1bslsjFO",
          "author": "@WhereonEarth4K",
          "authorImage": "https://yt3.ggpht.com/eGYI9iH4DF7Eb8QJYMMO2qNL_ls-4aNbWgY0tHLbCMrP4phySA3gN8SnhWB02TzySTEBGRXAIg=s48-c-k-c0x00ffffff-no-rj",
          "text": "Total forest coverage and old-growth forest loss aren't the same measurement. Romania's overall forested area has shifted with replanting and land-use changes, but the concern raised by conservation organizations like EuroNatur and Agent Green specifically targets primeval and virgin forest... the irreplaceable old-growth that once cut cannot be regrown on any human timescale. Both things can be true at once. We appreciate you pushing on the data... it's a topic that deserves precision.",
          "likeCount": 0,
          "publishedAt": "2026-05-02T03:12:10Z"
        },
        {
          "id": "UgzfTjGDncQuKkG_sWp4AaABAg.AW8_UsaPJQWAWHnTl2wG_N",
          "author": "@aimieward6298",
          "authorImage": "https://yt3.ggpht.com/ytc/AIdro_niHAflZLrcpSo8Bgp11F1bWBq4Tq76_iFw7LjBg54=s48-c-k-c0x00ffffff-no-rj",
          "text": "Did you miss the \"Primeval\" part?  That's old growth, hundreds to thousands of years old, it doesn't regrow for centuries. 🤦‍♀️",
          "likeCount": 1,
          "publishedAt": "2026-05-02T00:59:51Z"
        },
        {
          "id": "UgzfTjGDncQuKkG_sWp4AaABAg.AW8_UsaPJQWAWCdio0CxTR",
          "author": "@LindaCooper-i3f",
          "authorImage": "https://yt3.ggpht.com/ytc/AIdro_lDSJSDjAUAtuef0JTtAFXzaAujtvgNy8NZpTO3bv855fKQsLRkeAc5pd5228DEub_8fA=s48-c-k-c0x00ffffff-no-rj",
          "text": "And it’s a source of revenue for certain mountain villages, is it not?",
          "likeCount": 1,
          "publishedAt": "2026-04-30T00:58:27Z"
        }
      ]
    },
    {
      "id": "UgwFrhbaPIL6ElV0oKp4AaABAg",
      "author": "@danielracovitan9779",
      "authorImage": "https://yt3.ggpht.com/ytc/AIdro_m7dVGLqWohJXZdPaUmRXdN6FBPwodlDuohwKt5mMX7hxI=s48-c-k-c0x00ffffff-no-rj",
      "text": "no local calls the Carpathians \"Transylvanian Alps\" in Romania",
      "likeCount": 5,
      "publishedAt": "2026-04-28T08:53:17Z",
      "replyCount": 2,
      "replies": [
        {
          "id": "UgwFrhbaPIL6ElV0oKp4AaABAg.AW8LThXq9bdAWI1KUQhiAf",
          "author": "@WhereonEarth4K",
          "authorImage": "https://yt3.ggpht.com/eGYI9iH4DF7Eb8QJYMMO2qNL_ls-4aNbWgY0tHLbCMrP4phySA3gN8SnhWB02TzySTEBGRXAIg=s48-c-k-c0x00ffffff-no-rj",
          "text": "Fair point... it's a term you'll find in older English-language atlases and geographic references, but it's not how Romanians themselves refer to the mountains. We'll keep that in mind going forward. The Carpathians deserve their own name.",
          "likeCount": 1,
          "publishedAt": "2026-05-02T03:09:39Z"
        },
        {
          "id": "UgwFrhbaPIL6ElV0oKp4AaABAg.AW8LThXq9bdAWCdoHI_VN1",
          "author": "@LindaCooper-i3f",
          "authorImage": "https://yt3.ggpht.com/ytc/AIdro_lDSJSDjAUAtuef0JTtAFXzaAujtvgNy8NZpTO3bv855fKQsLRkeAc5pd5228DEub_8fA=s48-c-k-c0x00ffffff-no-rj",
          "text": "Maps in much older atlases do.",
          "likeCount": 1,
          "publishedAt": "2026-04-30T00:59:12Z"
        }
      ]
    },
    {
      "id": "UgwE-xidXQN6ktHT6nh4AaABAg",
      "author": "@gabordalmand1274",
      "authorImage": "https://yt3.ggpht.com/ytc/AIdro_mO90QpyC8L7voW7M-X-W85tfDJdICeWBQbXylGVhZTDA=s48-c-k-c0x00ffffff-no-rj",
      "text": "Brilliant show; far better then the rest! Additionally just one thing: to avoid the repeated Tatar/Mongol Invasions\nand the Militant Islam destructiv ambitions; the Hungarian Apostol State constructed over 1200 Fortresses to\ndefend their Western territorial hunger. Also; from the ironworks of the nearby industrial center of the Castle of VajdaHunyad (owner:Janos Hunyadi=Regent of Hunnia) the EIFFEL TOWER was elevated; see the BP Hungarian\nAcademy of Sciences \"ERDELY\" titled Monografie 3.Volume. And Abba Eban' s History of Judaism Chronologian\ndatabase about the nonstop terror against Erdely=TSylvania' s iron, salt and gold mines by the Roman Empire;\nfrom after Christus 100s to the 300s (29 Cesar!) what barbarian attackers were beaten back by the Szarmatians\n(bloodline folks from Etelkoz=SCYTHIA - see Herodotus Book IV.) = called the DACOSOK, dacoskodok, otherway\ncalled OPPOSITION FORCES against any enemy in Hunnis=Hungarian Linguatico's vocaibulary the VERB turned\ninto NOTION to describe the \"DAC\" of these people felt by every Roman incursons; see their 'Dacoskodo' attitude\nagainst ROMA=in actus/action by the 'DACIA'-los' army of the Scythian Szarmatians in the domain of later \"DACIA\".",
      "likeCount": 0,
      "publishedAt": "2026-04-27T09:58:07Z",
      "replyCount": 0,
      "replies": []
    },
    {
      "id": "UgzDKTdKynH2zKhg5VZ4AaABAg",
      "author": "@anifrunza6921",
      "authorImage": "https://yt3.ggpht.com/ytc/AIdro_l4u2zU_lNVzKKwDXIeigGyf_qCm-OP7b_-wc9vsTt18bg=s48-c-k-c0x00ffffff-no-rj",
      "text": "I was born close to Jibou,  Somes river. I was born premature, in a small village, they kept me in incubator for more than 2 weeks.  I didn’t know we had incubators back then, but yes we did. The small village was settled by my mother side family on 1474 ,  a greco-catolic priest and his cousin, a deacon. Since 1474, every first boy had to become a priest and continue the administration of the village, it was until 1952, when communists imprisoned members of family, doctors, students, priests and teachers. They build school, first school in the surroundings, which closed couple of years ago due to depopulation. I found the story only couple of years ago, and it is in city of Zalau, archives . The little village Tranis, which gave me the best memories.",
      "likeCount": 20,
      "publishedAt": "2026-04-27T03:45:31Z",
      "replyCount": 5,
      "replies": [
        {
          "id": "UgzDKTdKynH2zKhg5VZ4AaABAg.AW5DSmD2jrPAWK-AGv8UeB",
          "author": "@crc-d7s",
          "authorImage": "https://yt3.ggpht.com/ytc/AIdro_mcQV1blZZGdTiUX4cVsdf4Vy1SlQ-i1uoE3AVa33Ptbpk4q41f12BxxTp0ggs_2KzTew=s48-c-k-c0x00ffffff-no-rj",
          "text": "thanks for that, I will also trace my family from the archives of Zalau",
          "likeCount": 0,
          "publishedAt": "2026-05-02T21:29:16Z"
        },
        {
          "id": "UgzDKTdKynH2zKhg5VZ4AaABAg.AW5DSmD2jrPAWI1Vn5KSpd",
          "author": "@WhereonEarth4K",
          "authorImage": "https://yt3.ggpht.com/eGYI9iH4DF7Eb8QJYMMO2qNL_ls-4aNbWgY0tHLbCMrP4phySA3gN8SnhWB02TzySTEBGRXAIg=s48-c-k-c0x00ffffff-no-rj",
          "text": "A village settled in 1474 by a greco-catholic priest, with every firstborn son becoming a priest for nearly five centuries — that's the kind of continuity most of Europe can't even imagine anymore. The fact that you traced that history through the Zalău archives makes it even more remarkable. Thank you for sharing this. Stories like yours are the living record the documentary is about.",
          "likeCount": 2,
          "publishedAt": "2026-05-02T03:11:12Z"
        },
        {
          "id": "UgzDKTdKynH2zKhg5VZ4AaABAg.AW5DSmD2jrPAWCePnyYW8L",
          "author": "@LindaCooper-i3f",
          "authorImage": "https://yt3.ggpht.com/ytc/AIdro_lDSJSDjAUAtuef0JTtAFXzaAujtvgNy8NZpTO3bv855fKQsLRkeAc5pd5228DEub_8fA=s48-c-k-c0x00ffffff-no-rj",
          "text": "Sounds marvelous!",
          "likeCount": 1,
          "publishedAt": "2026-04-30T01:04:28Z"
        },
        {
          "id": "UgzDKTdKynH2zKhg5VZ4AaABAg.AW5DSmD2jrPAWCeMLsZ7HN",
          "author": "@LindaCooper-i3f",
          "authorImage": "https://yt3.ggpht.com/ytc/AIdro_lDSJSDjAUAtuef0JTtAFXzaAujtvgNy8NZpTO3bv855fKQsLRkeAc5pd5228DEub_8fA=s48-c-k-c0x00ffffff-no-rj",
          "text": "Very intriguing.",
          "likeCount": 1,
          "publishedAt": "2026-04-30T01:04:00Z"
        },
        {
          "id": "UgzDKTdKynH2zKhg5VZ4AaABAg.AW5DSmD2jrPAW9nzFcc7l8",
          "author": "@Luke-Skymaster",
          "authorImage": "https://yt3.ggpht.com/ytc/AIdro_kq2JMaYmMNo7ahz_HhVYGb9rKc9a3EEII73cX3aTsY41Q=s48-c-k-c0x00ffffff-no-rj",
          "text": "I was in Traniş for Christmas and new year back in 1986/87.  I was never a minute sober all that period. Good times",
          "likeCount": 1,
          "publishedAt": "2026-04-28T22:30:22Z"
        }
      ]
    },
    {
      "id": "Ugz2l8loeG_s-wUNSc14AaABAg",
      "author": "@fabiodeoliveiraribeiro1602",
      "authorImage": "https://yt3.ggpht.com/ytc/AIdro_lBsS30inM5y83h0B6BtJx500lo_Q83v-tMi2UrfeRs7g=s48-c-k-c0x00ffffff-no-rj",
      "text": "A nice place to visit, no doubt. No bullshit Trump Thulsa Doom Towers there.",
      "likeCount": 0,
      "publishedAt": "2026-04-25T21:46:42Z",
      "replyCount": 0,
      "replies": []
    }
  ]
}