{
  "videoId": "cqaD4TyxTiU",
  "disabled": false,
  "comments": [
    {
      "id": "UgxvMBNh9X-oTvUmB414AaABAg",
      "author": "@cesargabriel68",
      "authorImage": "https://yt3.ggpht.com/KPWC7P3W5BsC7eEEbPyB4p0GAn1nxXys1Yvqt0gPxCF8QfLCPY2tNSQRl5VN51wYc6q0_s6y=s48-c-k-c0x00ffffff-no-rj",
      "text": "Mi bis abuelo era Tomaso Suozzi y vino a Argentina desde la region de Basilicata Ciudad de Potenza . muchas gracias muy bueno !!!!!",
      "likeCount": 0,
      "publishedAt": "2026-05-29T02:50:06Z",
      "replyCount": 0,
      "replies": []
    },
    {
      "id": "UgxgmDpleM4H_BN2Ay54AaABAg",
      "author": "@VignolaPlus",
      "authorImage": "https://yt3.ggpht.com/ZO0RRvHntjVwZZN0X8_uU0ZkgDZbHa0aaYRey4BxSDaIAX2ib19RimrVm-a8Q5hI1xEkFeqQV1c=s48-c-k-c0x00ffffff-no-rj",
      "text": "Mi abuelo era de ahi basilicata potenza se vino a la argentina con sus hermanos. Carbone gilio .",
      "likeCount": 1,
      "publishedAt": "2026-05-23T23:48:17Z",
      "replyCount": 0,
      "replies": []
    }
  ]
}