{
  "videoId": "Nxqj9M_-IV4",
  "disabled": false,
  "comments": [
    {
      "id": "UgzL9CPSO7xL3wNhXvB4AaABAg",
      "author": "@ulisesmurua6093",
      "authorImage": "https://yt3.ggpht.com/ytc/AIdro_nCzvxkkeDi2b4YkcVQPiBfzjOTOBuatuEp9xkJAGaNtoQz=s48-c-k-c0x00ffffff-no-rj",
      "text": "Si",
      "likeCount": 3,
      "publishedAt": "2026-01-10T12:40:54Z",
      "replyCount": 0
    },
    {
      "id": "UgzgCbxOxuPY0ukSRSV4AaABAg",
      "author": "@MadelynSeguinot",
      "authorImage": "https://yt3.ggpht.com/ytc/AIdro_m5DHdJOQs40hzoitGNZg5x-fmV6OYmJoszNAslGR0idT_rVnRjRUDprHsTC8XFm7CrIA=s48-c-k-c0x00ffffff-no-rj",
      "text": "4❤😊",
      "likeCount": 1,
      "publishedAt": "2026-06-22T10:48:48Z",
      "replyCount": 0
    },
    {
      "id": "UgysNbymFTpn3j61TfB4AaABAg",
      "author": "@MadelynSeguinot",
      "authorImage": "https://yt3.ggpht.com/ytc/AIdro_m5DHdJOQs40hzoitGNZg5x-fmV6OYmJoszNAslGR0idT_rVnRjRUDprHsTC8XFm7CrIA=s48-c-k-c0x00ffffff-no-rj",
      "text": "Si 😊",
      "likeCount": 0,
      "publishedAt": "2026-06-22T10:50:41Z",
      "replyCount": 0
    },
    {
      "id": "UgyY05_hUGp9Uq9CmZR4AaABAg",
      "author": "@jorgeorozco3336",
      "authorImage": "https://yt3.ggpht.com/ytc/AIdro_lAGdQVJTYtHIgeiStwSqFET5CPr59ekSNPkmWgLYA=s48-c-k-c0x00ffffff-no-rj",
      "text": "Somos la peor plaga del mundo.",
      "likeCount": 0,
      "publishedAt": "2026-06-22T21:29:05Z",
      "replyCount": 0
    }
  ]
}