{
  "videoId": "pQqaVWfU47U",
  "disabled": false,
  "comments": [
    {
      "id": "UgwNECtltaJub5X-Ov54AaABAg",
      "author": "@patriciacabrero6205",
      "authorImage": "https://yt3.ggpht.com/ytc/AIdro_nKJcidUhtAPINphfZ3tfSLfv1hE_ZLhZKWYdiC1To=s48-c-k-c0x00ffffff-no-rj",
      "text": "LA PAZ IS NORTH , AND PUEBLA IS CENTRAL...DO A GOOD RESEARCH BEFORE UPLOADING THE VIDEO",
      "likeCount": 0,
      "publishedAt": "2026-06-12T04:32:22Z",
      "replyCount": 0,
      "replies": []
    }
  ]
}