{
  "videoId": "zTBmv-Gzf2w",
  "disabled": false,
  "comments": [
    {
      "id": "Ugz6avOJ6nIKISenHTN4AaABAg",
      "author": "@prede89",
      "authorImage": "https://yt3.ggpht.com/ytc/AIdro_miPlITpmLDp60M5vV9CsW1KXiWbta2YRDeOKp4PSJhgw=s48-c-k-c0x00ffffff-no-rj",
      "text": "Canyonlands is def underrated. It’s one of the best parks and much better than grand canyon. The canyons there are incredible! Canyons in canyons! More breathtaking than Grand Canyon which is one canyon",
      "likeCount": 0,
      "publishedAt": "2026-07-06T18:14:17Z",
      "replyCount": 0,
      "replies": []
    },
    {
      "id": "UgynU_XwMY9EBq3pBSB4AaABAg",
      "author": "@libiacollazos3842",
      "authorImage": "https://yt3.ggpht.com/ytc/AIdro_nUbB4-UaLuL-tyeDrr6X2H9IK9Ria7RdCIW074AaA=s48-c-k-c0x00ffffff-no-rj",
      "text": "The middle part was so cool",
      "likeCount": 0,
      "publishedAt": "2026-06-25T15:59:13Z",
      "replyCount": 0,
      "replies": []
    },
    {
      "id": "UgzCBl5-8zOPGDPKEAN4AaABAg",
      "author": "@dianasalazar4488",
      "authorImage": "https://yt3.ggpht.com/ytc/AIdro_kzNmd2RSuWUDL7T3pjn3Evxya2K_Yo9I4EqvbLsjrWcucG=s48-c-k-c0x00ffffff-no-rj",
      "text": "If you want to get technical and true to history, Yosemite would have been the first national park as advocated by John Muir. President Grant marked Yellowstone as the first US park, with Yosemite becoming  national park just over a decade later.",
      "likeCount": 0,
      "publishedAt": "2026-06-16T14:36:46Z",
      "replyCount": 0,
      "replies": []
    },
    {
      "id": "UgyN4qamh0A1LNGBpTl4AaABAg",
      "author": "@bunglejoy3645",
      "authorImage": "https://yt3.ggpht.com/ytc/AIdro_kv7-fRh9M9fb8DzvZpCJrk0XAPq76fuJJQY3T9gtQ=s48-c-k-c0x00ffffff-no-rj",
      "text": "What about zion  atio al park  .\nVideos ive seen on the park it looked  beautiful. \nIve never been abtoad never will.\nBut if youre lucky im not ,and live in usa.\nYou could holiday many national for a few years.",
      "likeCount": 0,
      "publishedAt": "2026-06-13T19:39:59Z",
      "replyCount": 0,
      "replies": []
    },
    {
      "id": "Ugz7lRh2vAduUCrDWRl4AaABAg",
      "author": "@Top7Daily-i9d",
      "authorImage": "https://yt3.ggpht.com/hm1mtyWp-31mX5BWYGjzAuySHr1iLEH33wjc9Hrqu_2kcJMJZHblNmQfQPgUyygHoCG07Iw1=s48-c-k-c0x00ffffff-no-rj",
      "text": "What an incredible collection of America's natural wonders! Every park has its own unique beauty, and the stunning footage makes you want to start planning a road trip right away. One suggestion for future videos would be to include a few hidden gems or lesser-known spots inside each park, along with the best seasons to visit and some practical travel tips. That would make this awesome guide even more useful for travelers. Great work!",
      "likeCount": 0,
      "publishedAt": "2026-06-06T07:00:47Z",
      "replyCount": 0,
      "replies": []
    },
    {
      "id": "UgwNHEg1H3nmPnjpZn54AaABAg",
      "author": "@playdoe848",
      "authorImage": "https://yt3.ggpht.com/ytc/AIdro_nkTj3KDNpqvInE7O72BNqqg-1f0YH8XEC8B4NM-TvQSg=s48-c-k-c0x00ffffff-no-rj",
      "text": "Cool DESTINATIONS!!!!🔥🔥🔥",
      "likeCount": 0,
      "publishedAt": "2026-05-29T11:58:14Z",
      "replyCount": 0,
      "replies": []
    },
    {
      "id": "Ugwv7BM_8cm7HUwCPTl4AaABAg",
      "author": "@MdRobiulIslam-z7t3g",
      "authorImage": "https://yt3.ggpht.com/ytc/AIdro_k18TQOefWzLa5SvdJmEE0dDZLfk4am4CaTqv-UUpCP4ll3lucs6Ttsxlbnh6UOy4Y8dw=s48-c-k-c0x00ffffff-no-rj",
      "text": "quick breakfast ideas",
      "likeCount": 0,
      "publishedAt": "2026-05-19T13:43:56Z",
      "replyCount": 0,
      "replies": []
    },
    {
      "id": "UgyGxV7EtVUiwhKcd2B4AaABAg",
      "author": "@benjauron5873",
      "authorImage": "https://yt3.ggpht.com/Y4d_RZV9h2oL6XnzIjccyfUEVsoM5W7yqUA2NnxpjJ51JIoGKYtUAXxPf0zznXQHBmhmEXa4=s48-c-k-c0x00ffffff-no-rj",
      "text": "You rank Death Valley and Glacier WAAAAAAY too low, and Everglades and Carlsbad Caverns WAAAAAAY too high.\nAnd I'm not trying to dis Everglades or Carlsbad, they're both great. But better than Death Valley or Glacier? In what national park did you find the crack you're smoking?",
      "likeCount": 0,
      "publishedAt": "2026-05-15T05:25:59Z",
      "replyCount": 0,
      "replies": []
    },
    {
      "id": "UgyqHPvSCUuwsCPGXTx4AaABAg",
      "author": "@MadeNewAJ",
      "authorImage": "https://yt3.ggpht.com/5Af5lftH78LRQN8KjnTgVUPXD9WfPQv2qu4b3128U93X3E27xF3eDr8qr8NZi75m_7oqvX6qA_Q=s48-c-k-c0x00ffffff-no-rj",
      "text": "Redwoods are too large to photograph in a regular photo. I literally had to use landscape photography to get one in. The trees are so large you could live in some of them. So fun and I miss it.",
      "likeCount": 0,
      "publishedAt": "2026-04-30T18:11:41Z",
      "replyCount": 0,
      "replies": []
    },
    {
      "id": "UgxodbFSljyL2939u1x4AaABAg",
      "author": "@MadeNewAJ",
      "authorImage": "https://yt3.ggpht.com/5Af5lftH78LRQN8KjnTgVUPXD9WfPQv2qu4b3128U93X3E27xF3eDr8qr8NZi75m_7oqvX6qA_Q=s48-c-k-c0x00ffffff-no-rj",
      "text": "Crater lake is under rated. 90 million trails in Crater lake? You don't give accurate information on some of these parks. But thanks it took me back to there",
      "likeCount": 0,
      "publishedAt": "2026-04-30T18:08:38Z",
      "replyCount": 0,
      "replies": []
    },
    {
      "id": "UgyZFa4Zh4MhnkeeNPV4AaABAg",
      "author": "@Voletiramprasad",
      "authorImage": "https://yt3.ggpht.com/ytc/AIdro_kwXum2n-4NDlJOLGEp-AbNEMn3kZG0sMudh8JcjvM-EwA=s48-c-k-c0x00ffffff-no-rj",
      "text": "11:49 looks like puppy’s face",
      "likeCount": 0,
      "publishedAt": "2026-04-25T23:45:04Z",
      "replyCount": 0,
      "replies": []
    },
    {
      "id": "Ugz0oJjWTCYn_xAlwkJ4AaABAg",
      "author": "@AnaghaBuwa",
      "authorImage": "https://yt3.ggpht.com/ytc/AIdro_meYAh6NPkc3qZ9RQbztfozX2jknUqc69hcasQTLZa7CCWY6MHmzRI1I6I59gYFhEiQXA=s48-c-k-c0x00ffffff-no-rj",
      "text": "🥰🥰nice",
      "likeCount": 0,
      "publishedAt": "2026-04-24T03:31:05Z",
      "replyCount": 0,
      "replies": []
    }
  ]
}